Workbook

Sheet 2019地市KPI导入模板
A1: 考核对象 | C1: 利润类指标（20分） | K1: 规模类指标（50分） | AM1: 重点产品指标（9分） | AO1: 渠道质量指标（16分） | AY1: 铁通指标（5分） | BC1: 加减分类 | BN1: kpi直接总分（加总） | BO1: 重点系数 | BT1: 考虑重点系数后的KPI总分（最终考核得分是=1-14项得分*70%+1-14项得分*30%*完成率）
A2: 运营中心 | B2: 地市 | C2: 直接毛利率-1季度指标 | D2: 直接毛利率-完成 | E2: 直接毛利率-完成比率 | F2: 直接毛利率-得分 | G2: 直接净利率-1季度指标 | H2: 直接净利率-完成 | I2: 直接净利率-完成比率 | J2: 直接净利率-得分 | K2: 运营收入-全年指标 （万元） | L2: 运营收入-1-3月累计完成 | M2: 运营收入-时间进度完成率 | N2: 运营收入-时间进度 | O2: 运营收入-1季度指标（万元） | P2: 运营收入-完成（万元） | Q2: 运营收入-得分 | R2: 自有品牌手机收入-全年指标 （万元） | S2: 自有品牌手机收入-1-3月累计完成 | T2: 自有品牌手机收入-时间进度完成率 | U2: 自有品牌手机收入-时间进度 | V2: 自有品牌手机收入-1季度指标（万元） | W2: 自有品牌手机收入-完成（万元） | X2: 自有品牌手机收入-得分 | Y2: 自有品牌智能硬件收入-全年指标（万元） | Z2: 自有品牌智能硬件收入-1-3月累计完成 | AA2: 自有品牌智能硬件收入-时间进度完成率 | AB2: 自有品牌智能硬件收入-时间进度 | AC2: 自有品牌智能硬件收入-1季度指标（万元） | AD2: 自有品牌智能硬件收入-完成（万元） | AE2: 自有品牌智能硬件收入-得分 | AF2: 非集团集采类别自有品牌智能硬件收入-全年指标（万元） | AG2: 非集团集采类别自有品牌智能硬件收入-1-3月累计完成 | AH2: 非集团集采类别自有品牌智能硬件收入-时间进度完成率 | AI2: 非集团集采类别自有品牌智能硬件收入-时间进度 | AJ2: 非集团集采类别自有品牌智能硬件收入-1季度指标（万元） | AK2: 非集团集采类别自有品牌智能硬件收入-完成（万元） | AL2: 非集团集采类别自有品牌智能硬件收入-得分 | AM2: 重点产品 | AN2: 重点产品得分 | AO2: 优质客户目标值-全年目标值（个） | AP2: 优质客户目标值-1季度指标 | AQ2: 优质客户目标值-1季度完成 | AR2: 优质客户目标值-1季度完成率 | AS2: 优质客户目标值-1季度得分 | AT2: KA客户手机销量目标值-全年目标值（台） | AU2: KA客户手机销量目标值-1季度指标 | AV2: KA客户手机销量目标值-1季度完成 | AW2: KA客户手机销量目标值-1季度完成率 | AX2: KA客户手机销量目标值-1季度得分 | AY2: 铁通终端销量-全年（万台） | AZ2: 铁通终端销量-1季度（万台） | BA2: 铁通终端销量-1季度完成 | BB2: 铁通终端销量-1季度得分 | BC2: 新零售厅店建设-厅店（个） | BD2: 新零售厅店建设-得分 | BE2: 售后净利率- 年度指标 | BF2: 售后净利率-1季度指标 | BG2: 售后净利率-1季度完成 | BH2: 售后净利率-1季度得分 | BI2: 直接净利率-值 | BJ2: 直接净利率-1季度得分 | BK2: 三个月以上应收账款占比-值 | BL2: 三个月以上应收账款占比-1季度得分 | BM2: 重大事项扣分项-值 | BN2: kpi直接总分（加总）-值 | BO2: 1季度重点系数A（权重50%):自主品牌手机收入指标/万元-值 | BP2: 1季度重点系数A完成率-值 | BQ2: 1季度重点系数B（权重50%):智能音箱发展目标/万台-值 | BR2: 1季度重点系数B完成率-值 | BS2: 完成率加总-值 | BT2: 考虑重点系数后的KPI总分-值
A3: 广州运营中心 | B3: 广州 | C3: 0.048 | E3: =D3/C3 -> 0 | F3: =MIN(10,IF(E3>=0.6,E3*10,0)) -> 0 | G3: 0.02 | I3: =H3/G3 -> 0 | J3: =MIN(10,IF(I3>=0.6,I3*10,0)) -> 0 | K3: 121903.76 | M3: =L3/(K3*90/365) -> 0 | N3: =L3/K3-90/365 -> -0.24657534 | O3: 42666.316 | Q3: =MIN(15,IF(P3/O3<0.6,0,P3/O3*15)) -> 0 | R3: 1711.0482 | S3: =VLOOKUP(B3,[1]自有品牌手机收入!$F$2:$G$23,2,0)/10000 -> 50.968754 | T3: =S3/(R3*90/365) -> 0.120807 | U3: =S3/R3-90/365 -> -0.21678731 | V3: 598.86689 | W3: =S3 -> 50.968754 | X3: =MIN(15,IF(W3/V3<0.6,0,W3/V3*15)) -> 0 | Y3: 8495.1577 | Z3: =VLOOKUP(B3,'[1]自有品牌智能硬件收入（已加配额制摊分）'!$H$2:$I$23,2,0)/10000 -> 3507.9184 | AA3: =Z3/(Y3*90/365) -> 1.6746667 | AB3: =Z3/Y3-90/365 -> 0.16635618 | AC3: 2973.3052 | AD3: =Z3 -> 3507.9184 | AE3: =MIN(10,IF(AD3/AC3<0.6,0,AD3/AC3*10)) -> 10 | AF3: 1665.3 | AG3: =VLOOKUP(B3,[1]非配额自有品牌智能硬件收入!$G$2:$H$23,2,0)/10000 -> 15.050401 | AH3: =AG3/(AF3*90/365) -> 0.036652697 | AI3: =AG3/AF3-90/365 -> -0.23753769 | AJ3: 582.855 | AK3: =AG3 -> 15.050401 | AL3: =MIN(10,IF(AK3/AJ3<0.6,0,AK3/AJ3*10)) -> 0 | AM3: 待发文后录入 | AN3: 2.0126183 | AO3: 71 | AP3: 71 | AQ3: =VLOOKUP(B3,[1]渠道类指标!$B$2:$F$22,5,0) -> 77 | AR3: =AQ3/AP3 -> 1.084507 | AS3: =MIN(8,IF(AR3>=0.8,AR3*8,0)) -> 8 | AT3: 116549.32 | AU3: 40792 | AV3: =VLOOKUP(B3,[1]渠道类指标!$B$2:$F$22,4,0) -> 4553 | AW3: =AV3/AU3 -> 0.11161502 | AX3: =MIN(8,IF(AW3>=0.8,AW3*8,0)) -> 0 | AY3: 2.58 | AZ3: 0.774 | BB3: =MIN(5,IF(BA3/AZ3<0.6,0,BA3/AZ3*5)) -> 0 | BD3: =MIN(5,BC3*2) -> 0 | BE3: 0.025 | BF3: 0.025 | BH3: =MIN(3,IF(BG3/BF3<0.6,0,BG3/BF3*3)) -> 0 | BI3: =H3 -> 0 | BO3: 598.86689 | BQ3: 4.69
A4: 广州运营中心 | B4: 肇庆 | C4: 0.048 | E4: =D4/C4 -> 0 | F4: =MIN(10,IF(E4>=0.6,E4*10,0)) -> 0 | G4: 0.02 | I4: =H4/G4 -> 0 | J4: =MIN(10,IF(I4>=0.6,I4*10,0)) -> 0 | K4: 6758.3524 | M4: =L4/(K4*90/365) -> 0 | N4: =L4/K4-90/365 -> -0.24657534 | O4: 2365.4233 | Q4: =MIN(15,IF(P4/O4<0.6,0,P4/O4*15)) -> 0 | R4: 549.92574 | S4: =VLOOKUP(B4,[1]自有品牌手机收入!$F$2:$G$23,2,0)/10000 -> 131.23382 | T4: =S4/(R4*90/365) -> 0.96781437 | U4: =S4/R4-90/365 -> -0.0079361835 | V4: 192.47401 | W4: =S4 -> 131.23382 | X4: =MIN(15,IF(W4/V4<0.6,0,W4/V4*15)) -> 10.227393 | Y4: 2027.8359 | Z4: =VLOOKUP(B4,'[1]自有品牌智能硬件收入（已加配额制摊分）'!$H$2:$I$23,2,0)/10000 -> 1185.2881 | AA4: =Z4/(Y4*90/365) -> 2.3705083 | AB4: =Z4/Y4-90/365 -> 0.33793354 | AC4: 709.74257 | AD4: =Z4 -> 1185.2881 | AE4: =MIN(10,IF(AD4/AC4<0.6,0,AD4/AC4*10)) -> 10 | AF4: 314.88293 | AG4: =VLOOKUP(B4,[1]非配额自有品牌智能硬件收入!$G$2:$H$23,2,0)/10000 -> 38.344752 | AH4: =AG4/(AF4*90/365) -> 0.49386378 | AI4: =AG4/AF4-90/365 -> -0.12480071 | AJ4: 110.20902 | AK4: =AG4 -> 38.344752 | AL4: =MIN(10,IF(AK4/AJ4<0.6,0,AK4/AJ4*10)) -> 0 | AM4: 待发文后录入 | AN4: 3.8916464 | AO4: 10 | AP4: 10 | AQ4: =VLOOKUP(B4,[1]渠道类指标!$B$2:$F$22,5,0) -> 10 | AR4: =AQ4/AP4 -> 1 | AS4: =MIN(8,IF(AR4>=0.8,AR4*8,0)) -> 8 | AT4: 18306.402 | AU4: 6407 | AV4: =VLOOKUP(B4,[1]渠道类指标!$B$2:$F$22,4,0) -> 2509 | AW4: =AV4/AU4 -> 0.39160293 | AX4: =MIN(8,IF(AW4>=0.8,AW4*8,0)) -> 0 | AY4: 0.3 | AZ4: 0.09 | BB4: =MIN(5,IF(BA4/AZ4<0.6,0,BA4/AZ4*5)) -> 0 | BD4: =MIN(5,BC4*2) -> 0 | BE4: 0.025 | BF4: 0.025 | BH4: =MIN(3,IF(BG4/BF4<0.6,0,BG4/BF4*3)) -> 0 | BI4: =H4 -> 0 | BO4: 192.47401 | BQ4: 0.73
A5: 广州运营中心 | B5: 清远 | C5: 0.048 | E5: =D5/C5 -> 0 | F5: =MIN(10,IF(E5>=0.6,E5*10,0)) -> 0 | G5: 0.02 | I5: =H5/G5 -> 0 | J5: =MIN(10,IF(I5>=0.6,I5*10,0)) -> 0 | K5: 6531.374 | M5: =L5/(K5*90/365) -> 0 | N5: =L5/K5-90/365 -> -0.24657534 | O5: 2285.9809 | Q5: =MIN(15,IF(P5/O5<0.6,0,P5/O5*15)) -> 0 | R5: 915.72739 | S5: =VLOOKUP(B5,[1]自有品牌手机收入!$F$2:$G$23,2,0)/10000 -> 177.14636 | T5: =S5/(R5*90/365) -> 0.78454234 | U5: =S5/R5-90/365 -> -0.053126546 | V5: 320.50459 | W5: =S5 -> 177.14636 | X5: =MIN(15,IF(W5/V5<0.6,0,W5/V5*15)) -> 0 | Y5: 2256.4863 | Z5: =VLOOKUP(B5,'[1]自有品牌智能硬件收入（已加配额制摊分）'!$H$2:$I$23,2,0)/10000 -> 986.66957 | AA5: =Z5/(Y5*90/365) -> 1.7733293 | AB5: =Z5/Y5-90/365 -> 0.19068394 | AC5: 789.7702 | AD5: =Z5 -> 986.66957 | AE5: =MIN(10,IF(AD5/AC5<0.6,0,AD5/AC5*10)) -> 10 | AF5: 358.61075 | AG5: =VLOOKUP(B5,[1]非配额自有品牌智能硬件收入!$G$2:$H$23,2,0)/10000 -> 64.902331 | AH5: =AG5/(AF5*90/365) -> 0.73398526 | AI5: =AG5/AF5-90/365 -> -0.065592675 | AJ5: 125.51376 | AK5: =AG5 -> 64.902331 | AL5: =MIN(10,IF(AK5/AJ5<0.6,0,AK5/AJ5*10)) -> 0 | AM5: 待发文后录入 | AN5: 3.7275486 | AO5: 10 | AP5: 10 | AQ5: =VLOOKUP(B5,[1]渠道类指标!$B$2:$F$22,5,0) -> 18 | AR5: =AQ5/AP5 -> 1.8 | AS5: =MIN(8,IF(AR5>=0.8,AR5*8,0)) -> 8 | AT5: 16059.12 | AU5: 5621 | AV5: =VLOOKUP(B5,[1]渠道类指标!$B$2:$F$22,4,0) -> 2075 | AW5: =AV5/AU5 -> 0.3691514 | AX5: =MIN(8,IF(AW5>=0.8,AW5*8,0)) -> 0 | AY5: 0.26 | AZ5: 0.078 | BB5: =MIN(5,IF(BA5/AZ5<0.6,0,BA5/AZ5*5)) -> 0 | BD5: =MIN(5,BC5*2) -> 0 | BE5: 0.025 | BF5: 0.025 | BH5: =MIN(3,IF(BG5/BF5<0.6,0,BG5/BF5*3)) -> 0 | BI5: =H5 -> 0 | BO5: 320.50459 | BQ5: 0.83
A6: 广州运营中心 | B6: 韶关 | C6: 0.048 | E6: =D6/C6 -> 0 | F6: =MIN(10,IF(E6>=0.6,E6*10,0)) -> 0 | G6: 0.02 | I6: =H6/G6 -> 0 | J6: =MIN(10,IF(I6>=0.6,I6*10,0)) -> 0 | K6: 6167.5789 | M6: =L6/(K6*90/365) -> 0 | N6: =L6/K6-90/365 -> -0.24657534 | O6: 2158.6526 | Q6: =MIN(15,IF(P6/O6<0.6,0,P6/O6*15)) -> 0 | R6: 570.33977 | S6: =VLOOKUP(B6,[1]自有品牌手机收入!$F$2:$G$23,2,0)/10000 -> 55.85483 | T6: =S6/(R6*90/365) -> 0.39717091 | U6: =S6/R6-90/365 -> -0.14864279 | V6: 199.61892 | W6: =S6 -> 55.85483 | X6: =MIN(15,IF(W6/V6<0.6,0,W6/V6*15)) -> 0 | Y6: 1727.427 | Z6: =VLOOKUP(B6,'[1]自有品牌智能硬件收入（已加配额制摊分）'!$H$2:$I$23,2,0)/10000 -> 1147.8148 | AA6: =Z6/(Y6*90/365) -> 2.6947748 | AB6: =Z6/Y6-90/365 -> 0.41788968 | AC6: 604.59943 | AD6: =Z6 -> 1147.8148 | AE6: =MIN(10,IF(AD6/AC6<0.6,0,AD6/AC6*10)) -> 10 | AF6: 264.81472 | AG6: =VLOOKUP(B6,[1]非配额自有品牌智能硬件收入!$G$2:$H$23,2,0)/10000 -> 17.600473 | AH6: =AG6/(AF6*90/365) -> 0.2695458 | AI6: =AG6/AF6-90/365 -> -0.18011199 | AJ6: 92.685151 | AK6: =AG6 -> 17.600473 | AL6: =MIN(10,IF(AK6/AJ6<0.6,0,AK6/AJ6*10)) -> 0 | AM6: 待发文后录入 | AN6: 3.5082024 | AO6: 17 | AP6: 17 | AQ6: =VLOOKUP(B6,[1]渠道类指标!$B$2:$F$22,5,0) -> 26 | AR6: =AQ6/AP6 -> 1.5294118 | AS6: =MIN(8,IF(AR6>=0.8,AR6*8,0)) -> 8 | AT6: 19992.119 | AU6: 6997 | AV6: =VLOOKUP(B6,[1]渠道类指标!$B$2:$F$22,4,0) -> 4572 | AW6: =AV6/AU6 -> 0.6534229 | AX6: =MIN(8,IF(AW6>=0.8,AW6*8,0)) -> 0 | AY6: 0.18 | AZ6: 0.054 | BB6: =MIN(5,IF(BA6/AZ6<0.6,0,BA6/AZ6*5)) -> 0 | BD6: =MIN(5,BC6*2) -> 0 | BE6: 0.025 | BF6: 0.025 | BH6: =MIN(3,IF(BG6/BF6<0.6,0,BG6/BF6*3)) -> 0 | BI6: =H6 -> 0 | BO6: 199.61892 | BQ6: 0.6
A7: 广州运营中心 | B7: 云浮 | C7: 0.048 | E7: =D7/C7 -> 0 | F7: =MIN(10,IF(E7>=0.6,E7*10,0)) -> 0 | G7: 0.02 | I7: =H7/G7 -> 0 | J7: =MIN(10,IF(I7>=0.6,I7*10,0)) -> 0 | K7: 3971.06 | M7: =L7/(K7*90/365) -> 0 | N7: =L7/K7-90/365 -> -0.24657534 | O7: 1389.871 | Q7: =MIN(15,IF(P7/O7<0.6,0,P7/O7*15)) -> 0 | R7: 332.76664 | S7: =VLOOKUP(B7,[1]自有品牌手机收入!$F$2:$G$23,2,0)/10000 -> 27.781248 | T7: =S7/(R7*90/365) -> 0.3385808 | U7: =S7/R7-90/365 -> -0.16308967 | V7: 116.46833 | W7: =S7 -> 27.781248 | X7: =MIN(15,IF(W7/V7<0.6,0,W7/V7*15)) -> 0 | Y7: 1262.1638 | Z7: =VLOOKUP(B7,'[1]自有品牌智能硬件收入（已加配额制摊分）'!$H$2:$I$23,2,0)/10000 -> 477.7609 | AA7: =Z7/(Y7*90/365) -> 1.5351303 | AB7: =Z7/Y7-90/365 -> 0.13194993 | AC7: 441.75733 | AD7: =Z7 -> 477.7609 | AE7: =MIN(10,IF(AD7/AC7<0.6,0,AD7/AC7*10)) -> 10 | AF7: 202.86168 | AG7: =VLOOKUP(B7,[1]非配额自有品牌智能硬件收入!$G$2:$H$23,2,0)/10000 -> 49.013484 | AH7: =AG7/(AF7*90/365) -> 0.97986426 | AI7: =AG7/AF7-90/365 -> -0.0049649775 | AJ7: 71.001587 | AK7: =AG7 -> 49.013484 | AL7: =MIN(10,IF(AK7/AJ7<0.6,0,AK7/AJ7*10)) -> 6.9031533 | AM7: 待发文后录入 | AN7: 4.7719595 | AO7: 12 | AP7: 12 | AQ7: =VLOOKUP(B7,[1]渠道类指标!$B$2:$F$22,5,0) -> 8 | AR7: =AQ7/AP7 -> 0.66666667 | AS7: =MIN(8,IF(AR7>=0.8,AR7*8,0)) -> 0 | AT7: 3822.5 | AU7: 1338 | AV7: =VLOOKUP(B7,[1]渠道类指标!$B$2:$F$22,4,0) -> 2432 | AW7: =AV7/AU7 -> 1.8176383 | AX7: =MIN(8,IF(AW7>=0.8,AW7*8,0)) -> 8 | AY7: 0.12 | AZ7: 0.036 | BB7: =MIN(5,IF(BA7/AZ7<0.6,0,BA7/AZ7*5)) -> 0 | BD7: =MIN(5,BC7*2) -> 0 | BE7: 0.025 | BF7: 0.025 | BH7: =MIN(3,IF(BG7/BF7<0.6,0,BG7/BF7*3)) -> 0 | BI7: =H7 -> 0 | BO7: 116.46833 | BQ7: 0.45
A8: 广州运营中心 | B8: 合计1 | C8: 0.048 | E8: =D8/C8 -> 0 | F8: =MIN(10,IF(E8>=0.6,E8*10,0)) -> 0 | G8: 0.02 | I8: =H8/G8 -> 0 | J8: =MIN(10,IF(I8>=0.6,I8*10,0)) -> 0 | K8: =SUM(K3:K7) -> 145332.12 | M8: =L8/(K8*90/365) -> 0 | N8: =L8/K8-90/365 -> -0.24657534 | O8: =SUM(O3:O7) -> 50866.244 | Q8: =SUM(Q3:Q7) -> 0 | R8: 4079.8078 | S8: =SUM(S3:S7) -> 442.98501 | T8: =S8/(R8*90/365) -> 0.44035171 | U8: =S8/R8-90/365 -> -0.13799547 | V8: 1427.9327 | W8: =S8 -> 442.98501 | X8: =MIN(15,IF(W8/V8<0.6,0,W8/V8*15)) -> 0 | Y8: =SUM(Y3:Y7) -> 15769.071 | Z8: =SUM(Z3:Z7) -> 7305.4518 | AA8: =Z8/(Y8*90/365) -> 1.8788467 | AB8: =Z8/Y8-90/365 -> 0.21670191 | AC8: =SUM(AC3:AC7) -> 5519.1747 | AD8: =Z8 -> 7305.4518 | AE8: =MIN(10,IF(AD8/AC8<0.6,0,AD8/AC8*10)) -> 10 | AF8: =SUM(AF3:AF7) -> 2806.4701 | AG8: =SUM(AG3:AG7) -> 184.91144 | AH8: =AG8/(AF8*90/365) -> 0.26721062 | AI8: =AG8/AF8-90/365 -> -0.18068779 | AJ8: =SUM(AJ3:AJ7) -> 982.26453 | AK8: =AG8 -> 184.91144 | AL8: =MIN(10,IF(AK8/AJ8<0.6,0,AK8/AJ8*10)) -> 0 | AM8: 待发文后录入 | AN8: =SUM(AN3:AN7) -> 17.911975 | AO8: =SUM(AO3:AO7) -> 120 | AP8: =SUM(AP3:AP7) -> 120 | AQ8: =SUM(AQ3:AQ7) -> 139 | AR8: =AQ8/AP8 -> 1.1583333 | AS8: =MIN(8,IF(AR8>=0.8,AR8*8,0)) -> 8 | AT8: =SUM(AT3:AT7) -> 174729.46 | AU8: =SUM(AU3:AU7) -> 61155 | AV8: =SUM(AV3:AV7) -> 16141 | AW8: =AV8/AU8 -> 0.2639359 | AX8: =MIN(8,IF(AW8>=0.8,AW8*8,0)) -> 0 | AY8: =SUM(AY3:AY7) -> 3.44 | AZ8: =SUM(AZ3:AZ7) -> 1.032 | BB8: =MIN(5,IF(BA8/AZ8<0.6,0,BA8/AZ8*5)) -> 0 | BD8: =MIN(5,BC8*2) -> 0 | BE8: 0.025 | BF8: 0.025 | BH8: =MIN(3,IF(BG8/BF8<0.6,0,BG8/BF8*3)) -> 0 | BI8: =H8 -> 0 | BO8: 1427.9327 | BQ8: =SUM(BQ3:BQ7) -> 7.3
A9: 深圳运营中心 | B9: 深圳 | C9: 0.048 | E9: =D9/C9 -> 0 | F9: =MIN(10,IF(E9>=0.6,E9*10,0)) -> 0 | G9: 0.02 | I9: =H9/G9 -> 0 | J9: =MIN(10,IF(I9>=0.6,I9*10,0)) -> 0 | K9: 131369.52 | M9: =L9/(K9*90/365) -> 0 | N9: =L9/K9-90/365 -> -0.24657534 | O9: 45979.332 | Q9: =MIN(15,IF(P9/O9<0.6,0,P9/O9*15)) -> 0 | R9: 1474.5425 | S9: =VLOOKUP(B9,[1]自有品牌手机收入!$F$2:$G$23,2,0)/10000 -> 24.955766 | T9: =S9/(R9*90/365) -> 0.068637898 | U9: =S9/R9-90/365 -> -0.22965093 | V9: 516.08987 | W9: =S9 -> 24.955766 | X9: =MIN(15,IF(W9/V9<0.6,0,W9/V9*15)) -> 0 | Y9: 7884.8421 | Z9: =VLOOKUP(B9,'[1]自有品牌智能硬件收入（已加配额制摊分）'!$H$2:$I$23,2,0)/10000 -> 3097.7941 | AA9: =Z9/(Y9*90/365) -> 1.5933453 | AB9: =Z9/Y9-90/365 -> 0.14630432 | AC9: 2759.6947 | AD9: =Z9 -> 3097.7941 | AE9: =MIN(10,IF(AD9/AC9<0.6,0,AD9/AC9*10)) -> 10 | AF9: 1581.235 | AG9: =VLOOKUP(B9,[1]非配额自有品牌智能硬件收入!$G$2:$H$23,2,0)/10000 -> 18.643862 | AH9: =AG9/(AF9*90/365) -> 0.047817823 | AI9: =AG9/AF9-90/365 -> -0.23478465 | AJ9: 553.43227 | AK9: =AG9 -> 18.643862 | AL9: =MIN(10,IF(AK9/AJ9<0.6,0,AK9/AJ9*10)) -> 0 | AM9: 待发文后录入 | AN9: 1.7764778 | AO9: 62 | AP9: 62 | AQ9: =VLOOKUP(B9,[1]渠道类指标!$B$2:$F$22,5,0) -> 82 | AR9: =AQ9/AP9 -> 1.3225806 | AS9: =MIN(8,IF(AR9>=0.8,AR9*8,0)) -> 8 | AT9: 198350.52 | AU9: 69423 | AV9: =VLOOKUP(B9,[1]渠道类指标!$B$2:$F$22,4,0) -> 5909 | AW9: =AV9/AU9 -> 0.085115884 | AX9: =MIN(8,IF(AW9>=0.8,AW9*8,0)) -> 0 | AY9: 1.8 | AZ9: 0.54 | BB9: =MIN(5,IF(BA9/AZ9<0.6,0,BA9/AZ9*5)) -> 0 | BD9: =MIN(5,BC9*2) -> 0 | BE9: 0.025 | BF9: 0.025 | BH9: =MIN(3,IF(BG9/BF9<0.6,0,BG9/BF9*3)) -> 0 | BI9: =H9 -> 0 | BO9: 516.08987 | BQ9: 4.51
A10: 深圳运营中心 | B10: 汕头 | C10: 0.048 | E10: =D10/C10 -> 0 | F10: =MIN(10,IF(E10>=0.6,E10*10,0)) -> 0 | G10: 0.02 | I10: =H10/G10 -> 0 | J10: =MIN(10,IF(I10>=0.6,I10*10,0)) -> 0 | K10: 12715.403 | M10: =L10/(K10*90/365) -> 0 | N10: =L10/K10-90/365 -> -0.24657534 | O10: 4450.3911 | Q10: =MIN(15,IF(P10/O10<0.6,0,P10/O10*15)) -> 0 | R10: 714.71893 | S10: =VLOOKUP(B10,[1]自有品牌手机收入!$F$2:$G$23,2,0)/10000 -> 275.20818 | T10: =S10/(R10*90/365) -> 1.5616237 | U10: =S10/R10-90/365 -> 0.13848257 | V10: 250.15163 | W10: =S10 -> 275.20818 | X10: =MIN(15,IF(W10/V10<0.6,0,W10/V10*15)) -> 15 | Y10: 3350.143 | Z10: =VLOOKUP(B10,'[1]自有品牌智能硬件收入（已加配额制摊分）'!$H$2:$I$23,2,0)/10000 -> 2242.3935 | AA10: =Z10/(Y10*90/365) -> 2.7145561 | AB10: =Z10/Y10-90/365 -> 0.42276726 | AC10: 1172.5501 | AD10: =Z10 -> 2242.3935 | AE10: =MIN(10,IF(AD10/AC10<0.6,0,AD10/AC10*10)) -> 10 | AF10: 546.2786 | AG10: =VLOOKUP(B10,[1]非配额自有品牌智能硬件收入!$G$2:$H$23,2,0)/10000 -> 125.42794 | AH10: =AG10/(AF10*90/365) -> 0.9311732 | AI10: =AG10/AF10-90/365 -> -0.016970991 | AJ10: 191.19751 | AK10: =AG10 -> 125.42794 | AL10: =MIN(10,IF(AK10/AJ10<0.6,0,AK10/AJ10*10)) -> 6.5601243 | AM10: 待发文后录入 | AN10: 4.1520591 | AO10: 33 | AP10: 33 | AQ10: =VLOOKUP(B10,[1]渠道类指标!$B$2:$F$22,5,0) -> 42 | AR10: =AQ10/AP10 -> 1.2727273 | AS10: =MIN(8,IF(AR10>=0.8,AR10*8,0)) -> 8 | AT10: 16741.76 | AU10: 5860 | AV10: =VLOOKUP(B10,[1]渠道类指标!$B$2:$F$22,4,0) -> 2222 | AW10: =AV10/AU10 -> 0.37918089 | AX10: =MIN(8,IF(AW10>=0.8,AW10*8,0)) -> 0 | AY10: 0.58 | AZ10: 0.174 | BB10: =MIN(5,IF(BA10/AZ10<0.6,0,BA10/AZ10*5)) -> 0 | BD10: =MIN(5,BC10*2) -> 0 | BE10: 0.025 | BF10: 0.025 | BH10: =MIN(3,IF(BG10/BF10<0.6,0,BG10/BF10*3)) -> 0 | BI10: =H10 -> 0 | BO10: 250.15163 | BQ10: 1.31
A11: 深圳运营中心 | B11: 揭阳 | C11: 0.048 | E11: =D11/C11 -> 0 | F11: =MIN(10,IF(E11>=0.6,E11*10,0)) -> 0 | G11: 0.02 | I11: =H11/G11 -> 0 | J11: =MIN(10,IF(I11>=0.6,I11*10,0)) -> 0 | K11: 8205.9678 | M11: =L11/(K11*90/365) -> 0 | N11: =L11/K11-90/365 -> -0.24657534 | O11: 2872.0887 | Q11: =MIN(15,IF(P11/O11<0.6,0,P11/O11*15)) -> 0 | R11: 307.11015 | S11: =VLOOKUP(B11,[1]自有品牌手机收入!$F$2:$G$23,2,0)/10000 -> 64.99317 | T11: =S11/(R11*90/365) -> 0.85826994 | U11: =S11/R11-90/365 -> -0.034947139 | V11: 107.48855 | W11: =S11 -> 64.99317 | X11: =MIN(15,IF(W11/V11<0.6,0,W11/V11*15)) -> 9.0697801 | Y11: 2637.6228 | Z11: =VLOOKUP(B11,'[1]自有品牌智能硬件收入（已加配额制摊分）'!$H$2:$I$23,2,0)/10000 -> 1729.9065 | AA11: =Z11/(Y11*90/365) -> 2.6598693 | AB11: =Z11/Y11-90/365 -> 0.40928284 | AC11: 923.16799 | AD11: =Z11 -> 1729.9065 | AE11: =MIN(10,IF(AD11/AC11<0.6,0,AD11/AC11*10)) -> 10 | AF11: 427.5973 | AG11: =VLOOKUP(B11,[1]非配额自有品牌智能硬件收入!$G$2:$H$23,2,0)/10000 -> 105.54791 | AH11: =AG11/(AF11*90/365) -> 1.0010713 | AI11: =AG11/AF11-90/365 -> 0.00026416147 | AJ11: 149.65905 | AK11: =AG11 -> 105.54791 | AL11: =MIN(10,IF(AK11/AJ11<0.6,0,AK11/AJ11*10)) -> 7.0525573 | AM11: 待发文后录入 | AN11: 2.1145349 | AO11: 14 | AP11: 14 | AQ11: =VLOOKUP(B11,[1]渠道类指标!$B$2:$F$22,5,0) -> 13 | AR11: =AQ11/AP11 -> 0.92857143 | AS11: =MIN(8,IF(AR11>=0.8,AR11*8,0)) -> 7.4285714 | AT11: 3317.6 | AU11: 1161 | AV11: =VLOOKUP(B11,[1]渠道类指标!$B$2:$F$22,4,0) -> 1744 | AW11: =AV11/AU11 -> 1.5021533 | AX11: =MIN(8,IF(AW11>=0.8,AW11*8,0)) -> 8 | AY11: 0.24 | AZ11: 0.072 | BB11: =MIN(5,IF(BA11/AZ11<0.6,0,BA11/AZ11*5)) -> 0 | BD11: =MIN(5,BC11*2) -> 0 | BE11: 0.025 | BF11: 0.025 | BH11: =MIN(3,IF(BG11/BF11<0.6,0,BG11/BF11*3)) -> 0 | BI11: =H11 -> 0 | BO11: 107.48855 | BQ11: 0.99
A12: 深圳运营中心 | B12: 梅州 | C12: 0.048 | E12: =D12/C12 -> 0 | F12: =MIN(10,IF(E12>=0.6,E12*10,0)) -> 0 | G12: 0.02 | I12: =H12/G12 -> 0 | J12: =MIN(10,IF(I12>=0.6,I12*10,0)) -> 0 | K12: 7415.6629 | M12: =L12/(K12*90/365) -> 0 | N12: =L12/K12-90/365 -> -0.24657534 | O12: 2595.482 | Q12: =MIN(15,IF(P12/O12<0.6,0,P12/O12*15)) -> 0 | R12: 531.2093 | S12: =VLOOKUP(B12,[1]自有品牌手机收入!$F$2:$G$23,2,0)/10000 -> 123.17975 | T12: =S12/(R12*90/365) -> 0.94042464 | U12: =S12/R12-90/365 -> -0.014689815 | V12: 185.92326 | W12: =S12 -> 123.17975 | X12: =MIN(15,IF(W12/V12<0.6,0,W12/V12*15)) -> 9.9379512 | Y12: 2296.8266 | Z12: =VLOOKUP(B12,'[1]自有品牌智能硬件收入（已加配额制摊分）'!$H$2:$I$23,2,0)/10000 -> 1097.0641 | AA12: =Z12/(Y12*90/365) -> 1.9371095 | AB12: =Z12/Y12-90/365 -> 0.23106809 | AC12: 803.88931 | AD12: =Z12 -> 1097.0641 | AE12: =MIN(10,IF(AD12/AC12<0.6,0,AD12/AC12*10)) -> 10 | AF12: 350.46311 | AG12: =VLOOKUP(B12,[1]非配额自有品牌智能硬件收入!$G$2:$H$23,2,0)/10000 -> 25.771035 | AH12: =AG12/(AF12*90/365) -> 0.29822216 | AI12: =AG12/AF12-90/365 -> -0.17304111 | AJ12: 122.66209 | AK12: =AG12 -> 25.771035 | AL12: =MIN(10,IF(AK12/AJ12<0.6,0,AK12/AJ12*10)) -> 0 | AM12: 待发文后录入 | AN12: 3.4350962 | AO12: 31 | AP12: 31 | AQ12: =VLOOKUP(B12,[1]渠道类指标!$B$2:$F$22,5,0) -> 35 | AR12: =AQ12/AP12 -> 1.1290323 | AS12: =MIN(8,IF(AR12>=0.8,AR12*8,0)) -> 8 | AT12: 14574.139 | AU12: 5101 | AV12: =VLOOKUP(B12,[1]渠道类指标!$B$2:$F$22,4,0) -> 16686 | AW12: =AV12/AU12 -> 3.2711233 | AX12: =MIN(8,IF(AW12>=0.8,AW12*8,0)) -> 8 | AY12: 0.3 | AZ12: 0.09 | BB12: =MIN(5,IF(BA12/AZ12<0.6,0,BA12/AZ12*5)) -> 0 | BD12: =MIN(5,BC12*2) -> 0 | BE12: 0.025 | BF12: 0.025 | BH12: =MIN(3,IF(BG12/BF12<0.6,0,BG12/BF12*3)) -> 0 | BI12: =H12 -> 0 | BO12: 185.92326 | BQ12: 0.79
A13: 深圳运营中心 | B13: 潮州 | C13: 0.048 | E13: =D13/C13 -> 0 | F13: =MIN(10,IF(E13>=0.6,E13*10,0)) -> 0 | G13: 0.02 | I13: =H13/G13 -> 0 | J13: =MIN(10,IF(I13>=0.6,I13*10,0)) -> 0 | K13: 5115.1099 | M13: =L13/(K13*90/365) -> 0 | N13: =L13/K13-90/365 -> -0.24657534 | O13: 1790.2885 | Q13: =MIN(15,IF(P13/O13<0.6,0,P13/O13*15)) -> 0 | R13: 474.89651 | S13: =VLOOKUP(B13,[1]自有品牌手机收入!$F$2:$G$23,2,0)/10000 -> 91.971036 | T13: =S13/(R13*90/365) -> 0.78542091 | U13: =S13/R13-90/365 -> -0.052909913 | V13: 166.21378 | W13: =S13 -> 91.971036 | X13: =MIN(15,IF(W13/V13<0.6,0,W13/V13*15)) -> 0 | Y13: 1649.0526 | Z13: =VLOOKUP(B13,'[1]自有品牌智能硬件收入（已加配额制摊分）'!$H$2:$I$23,2,0)/10000 -> 850.84736 | AA13: =Z13/(Y13*90/365) -> 2.0925098 | AB13: =Z13/Y13-90/365 -> 0.26938598 | AC13: 577.16841 | AD13: =Z13 -> 850.84736 | AE13: =MIN(10,IF(AD13/AC13<0.6,0,AD13/AC13*10)) -> 10 | AF13: 258.91242 | AG13: =VLOOKUP(B13,[1]非配额自有品牌智能硬件收入!$G$2:$H$23,2,0)/10000 -> 166.1284 | AH13: =AG13/(AF13*90/365) -> 2.6022041 | AI13: =AG13/AF13-90/365 -> 0.39506402 | AJ13: 90.619346 | AK13: =AG13 -> 166.1284 | AL13: =MIN(10,IF(AK13/AJ13<0.6,0,AK13/AJ13*10)) -> 10 | AM13: 待发文后录入 | AN13: 2.9122725 | AO13: 15 | AP13: 15 | AQ13: =VLOOKUP(B13,[1]渠道类指标!$B$2:$F$22,5,0) -> 17 | AR13: =AQ13/AP13 -> 1.1333333 | AS13: =MIN(8,IF(AR13>=0.8,AR13*8,0)) -> 8 | AT13: 21475.425 | AU13: 7516 | AV13: =VLOOKUP(B13,[1]渠道类指标!$B$2:$F$22,4,0) -> 6756 | AW13: =AV13/AU13 -> 0.89888238 | AX13: =MIN(8,IF(AW13>=0.8,AW13*8,0)) -> 7.1910591 | AY13: 0.14 | AZ13: 0.042 | BB13: =MIN(5,IF(BA13/AZ13<0.6,0,BA13/AZ13*5)) -> 0 | BD13: =MIN(5,BC13*2) -> 0 | BE13: 0.025 | BF13: 0.025 | BH13: =MIN(3,IF(BG13/BF13<0.6,0,BG13/BF13*3)) -> 0 | BI13: =H13 -> 0 | BO13: 166.21378 | BQ13: 0.59
A14: 深圳运营中心 | B14: 汕尾 | C14: 0.048 | E14: =D14/C14 -> 0 | F14: =MIN(10,IF(E14>=0.6,E14*10,0)) -> 0 | G14: 0.02 | I14: =H14/G14 -> 0 | J14: =MIN(10,IF(I14>=0.6,I14*10,0)) -> 0 | K14: 5057.3575 | M14: =L14/(K14*90/365) -> 0 | N14: =L14/K14-90/365 -> -0.24657534 | O14: 1770.0751 | Q14: =MIN(15,IF(P14/O14<0.6,0,P14/O14*15)) -> 0 | R14: 133.34812 | S14: =VLOOKUP(B14,[1]自有品牌手机收入!$F$2:$G$23,2,0)/10000 -> 23.976644 | T14: =S14/(R14*90/365) -> 0.72920869 | U14: =S14/R14-90/365 -> -0.066770459 | V14: 46.671844 | W14: =S14 -> 23.976644 | X14: =MIN(15,IF(W14/V14<0.6,0,W14/V14*15)) -> 0 | Y14: 1224.1447 | Z14: =VLOOKUP(B14,'[1]自有品牌智能硬件收入（已加配额制摊分）'!$H$2:$I$23,2,0)/10000 -> 453.74724 | AA14: =Z14/(Y14*90/365) -> 1.5032514 | AB14: =Z14/Y14-90/365 -> 0.12408938 | AC14: 428.45063 | AD14: =Z14 -> 453.74724 | AE14: =MIN(10,IF(AD14/AC14<0.6,0,AD14/AC14*10)) -> 10 | AF14: 186.96581 | AG14: =VLOOKUP(B14,[1]非配额自有品牌智能硬件收入!$G$2:$H$23,2,0)/10000 -> 0.003276 | AH14: =AG14/(AF14*90/365) -> 7.1061121e-05 | AI14: =AG14/AF14-90/365 -> -0.24655782 | AJ14: 65.438033 | AK14: =AG14 -> 0.003276 | AL14: =MIN(10,IF(AK14/AJ14<0.6,0,AK14/AJ14*10)) -> 0 | AM14: 待发文后录入 | AN14: 3.5815219 | AO14: 10 | AP14: 10 | AQ14: =VLOOKUP(B14,[1]渠道类指标!$B$2:$F$22,5,0) -> 12 | AR14: =AQ14/AP14 -> 1.2 | AS14: =MIN(8,IF(AR14>=0.8,AR14*8,0)) -> 8 | AT14: 1690 | AU14: 592 | AV14: =VLOOKUP(B14,[1]渠道类指标!$B$2:$F$22,4,0) -> 58 | AW14: =AV14/AU14 -> 0.097972973 | AX14: =MIN(8,IF(AW14>=0.8,AW14*8,0)) -> 0 | AY14: 0.12 | AZ14: 0.036 | BB14: =MIN(5,IF(BA14/AZ14<0.6,0,BA14/AZ14*5)) -> 0 | BD14: =MIN(5,BC14*2) -> 0 | BE14: 0.025 | BF14: 0.025 | BH14: =MIN(3,IF(BG14/BF14<0.6,0,BG14/BF14*3)) -> 0 | BI14: =H14 -> 0 | BO14: 46.671844 | BQ14: 0.44
A15: 深圳运营中心 | B15: 合计2 | C15: 0.048 | E15: =D15/C15 -> 0 | F15: =MIN(10,IF(E15>=0.6,E15*10,0)) -> 0 | G15: 0.02 | I15: =H15/G15 -> 0 | J15: =MIN(10,IF(I15>=0.6,I15*10,0)) -> 0 | K15: =SUM(K9:K14) -> 169879.02 | M15: =L15/(K15*90/365) -> 0 | N15: =L15/K15-90/365 -> -0.24657534 | O15: =SUM(O9:O14) -> 59457.657 | Q15: =SUM(Q9:Q14) -> 0 | R15: 3635.8255 | S15: =SUM(S9:S14) -> 604.28454 | T15: =S15/(R15*90/365) -> 0.67404487 | U15: =S15/R15-90/365 -> -0.080372497 | V15: 1272.5389 | W15: =S15 -> 604.28454 | X15: =MIN(15,IF(W15/V15<0.6,0,W15/V15*15)) -> 0 | Y15: =SUM(Y9:Y14) -> 19042.632 | Z15: =SUM(Z9:Z14) -> 9471.7528 | AA15: =Z15/(Y15*90/365) -> 2.0172222 | AB15: =Z15/Y15-90/365 -> 0.25082191 | AC15: =SUM(AC9:AC14) -> 6664.9211 | AD15: =Z15 -> 9471.7528 | AE15: =MIN(10,IF(AD15/AC15<0.6,0,AD15/AC15*10)) -> 10 | AF15: =SUM(AF9:AF14) -> 3351.4523 | AG15: =SUM(AG9:AG14) -> 441.52242 | AH15: =AG15/(AF15*90/365) -> 0.53428143 | AI15: =AG15/AF15-90/365 -> -0.11483472 | AJ15: =SUM(AJ9:AJ14) -> 1173.0083 | AK15: =AG15 -> 441.52242 | AL15: =MIN(10,IF(AK15/AJ15<0.6,0,AK15/AJ15*10)) -> 0 | AM15: 待发文后录入 | AN15: =SUM(AN9:AN14) -> 17.971962 | AO15: =SUM(AO9:AO14) -> 165 | AP15: =SUM(AP9:AP14) -> 165 | AQ15: =SUM(AQ9:AQ14) -> 201 | AR15: =AQ15/AP15 -> 1.2181818 | AS15: =MIN(8,IF(AR15>=0.8,AR15*8,0)) -> 8 | AT15: =SUM(AT9:AT14) -> 256149.45 | AU15: =SUM(AU9:AU14) -> 89653 | AV15: =SUM(AV9:AV14) -> 33375 | AW15: =AV15/AU15 -> 0.37226864 | AX15: =MIN(8,IF(AW15>=0.8,AW15*8,0)) -> 0 | AY15: =SUM(AY9:AY14) -> 3.18 | AZ15: =SUM(AZ9:AZ14) -> 0.954 | BB15: =MIN(5,IF(BA15/AZ15<0.6,0,BA15/AZ15*5)) -> 0 | BD15: =MIN(5,BC15*2) -> 0 | BE15: 0.025 | BF15: 0.025 | BH15: =MIN(3,IF(BG15/BF15<0.6,0,BG15/BF15*3)) -> 0 | BI15: =H15 -> 0 | BO15: 1272.5389 | BQ15: =SUM(BQ9:BQ14) -> 8.63
A16: 东莞运营中心 | B16: 东莞 | C16: 0.048 | E16: =D16/C16 -> 0 | F16: =MIN(10,IF(E16>=0.6,E16*10,0)) -> 0 | G16: 0.02 | I16: =H16/G16 -> 0 | J16: =MIN(10,IF(I16>=0.6,I16*10,0)) -> 0 | K16: 77462.974 | M16: =L16/(K16*90/365) -> 0 | N16: =L16/K16-90/365 -> -0.24657534 | O16: 27112.041 | Q16: =MIN(15,IF(P16/O16<0.6,0,P16/O16*15)) -> 0 | R16: 1215.4387 | S16: =VLOOKUP(B16,[1]自有品牌手机收入!$F$2:$G$23,2,0)/10000 -> 22.74087 | T16: =S16/(R16*90/365) -> 0.075879485 | U16: =S16/R16-90/365 -> -0.22786533 | V16: 425.40354 | W16: =S16 -> 22.74087 | X16: =MIN(15,IF(W16/V16<0.6,0,W16/V16*15)) -> 0 | Y16: 5797.1972 | Z16: =VLOOKUP(B16,'[1]自有品牌智能硬件收入（已加配额制摊分）'!$H$2:$I$23,2,0)/10000 -> 2679.7864 | AA16: =Z16/(Y16*90/365) -> 1.8747029 | AB16: =Z16/Y16-90/365 -> 0.21568018 | AC16: 2029.019 | AD16: =Z16 -> 2679.7864 | AE16: =MIN(10,IF(AD16/AC16<0.6,0,AD16/AC16*10)) -> 10 | AF16: 1112.5606 | AG16: =VLOOKUP(B16,[1]非配额自有品牌智能硬件收入!$G$2:$H$23,2,0)/10000 -> 10.808563 | AH16: =AG16/(AF16*90/365) -> 0.039399858 | AI16: =AG16/AF16-90/365 -> -0.23686031 | AJ16: 389.39619 | AK16: =AG16 -> 10.808563 | AL16: =MIN(10,IF(AK16/AJ16<0.6,0,AK16/AJ16*10)) -> 0 | AM16: 待发文后录入 | AN16: 1.2518178 | AO16: 49 | AP16: 49 | AQ16: =VLOOKUP(B16,[1]渠道类指标!$B$2:$F$22,5,0) -> 131 | AR16: =AQ16/AP16 -> 2.6734694 | AS16: =MIN(8,IF(AR16>=0.8,AR16*8,0)) -> 8 | AT16: 162093.72 | AU16: 56733 | AV16: =VLOOKUP(B16,[1]渠道类指标!$B$2:$F$22,4,0) -> 8192 | AW16: =AV16/AU16 -> 0.14439568 | AX16: =MIN(8,IF(AW16>=0.8,AW16*8,0)) -> 0 | AY16: 0.86 | AZ16: 0.258 | BB16: =MIN(5,IF(BA16/AZ16<0.6,0,BA16/AZ16*5)) -> 0 | BD16: =MIN(5,BC16*2) -> 0 | BE16: 0.025 | BF16: 0.025 | BH16: =MIN(3,IF(BG16/BF16<0.6,0,BG16/BF16*3)) -> 0 | BI16: =H16 -> 0 | BO16: 425.40354 | BQ16: 3.05
A17: 东莞运营中心 | B17: 中山 | C17: 0.048 | E17: =D17/C17 -> 0 | F17: =MIN(10,IF(E17>=0.6,E17*10,0)) -> 0 | G17: 0.02 | I17: =H17/G17 -> 0 | J17: =MIN(10,IF(I17>=0.6,I17*10,0)) -> 0 | K17: 10112.08 | M17: =L17/(K17*90/365) -> 0 | N17: =L17/K17-90/365 -> -0.24657534 | O17: 3539.2281 | Q17: =MIN(15,IF(P17/O17<0.6,0,P17/O17*15)) -> 0 | R17: 843.28211 | S17: =VLOOKUP(B17,[1]自有品牌手机收入!$F$2:$G$23,2,0)/10000 -> 26.376398 | T17: =S17/(R17*90/365) -> 0.12685073 | U17: =S17/R17-90/365 -> -0.21529708 | V17: 295.14874 | W17: =S17 -> 26.376398 | X17: =MIN(15,IF(W17/V17<0.6,0,W17/V17*15)) -> 0 | Y17: 3459.4354 | Z17: =VLOOKUP(B17,'[1]自有品牌智能硬件收入（已加配额制摊分）'!$H$2:$I$23,2,0)/10000 -> 364.67077 | AA17: =Z17/(Y17*90/365) -> 0.42750981 | AB17: =Z17/Y17-90/365 -> -0.14116196 | AC17: 1210.8024 | AD17: =Z17 -> 364.67077 | AE17: =MIN(10,IF(AD17/AC17<0.6,0,AD17/AC17*10)) -> 0 | AF17: 605.29232 | AG17: =VLOOKUP(B17,[1]非配额自有品牌智能硬件收入!$G$2:$H$23,2,0)/10000 -> 5.696632 | AH17: =AG17/(AF17*90/365) -> 0.038168347 | AI17: =AG17/AF17-90/365 -> -0.23716397 | AJ17: 211.85231 | AK17: =AG17 -> 5.696632 | AL17: =MIN(10,IF(AK17/AJ17<0.6,0,AK17/AJ17*10)) -> 0 | AM17: 待发文后录入 | AN17: 3.321395 | AO17: 23 | AP17: 23 | AQ17: =VLOOKUP(B17,[1]渠道类指标!$B$2:$F$22,5,0) -> 39 | AR17: =AQ17/AP17 -> 1.6956522 | AS17: =MIN(8,IF(AR17>=0.8,AR17*8,0)) -> 8 | AT17: 38377 | AU17: 13432 | AV17: =VLOOKUP(B17,[1]渠道类指标!$B$2:$F$22,4,0) -> 9234 | AW17: =AV17/AU17 -> 0.68746278 | AX17: =MIN(8,IF(AW17>=0.8,AW17*8,0)) -> 0 | AY17: 0.54 | AZ17: 0.162 | BB17: =MIN(5,IF(BA17/AZ17<0.6,0,BA17/AZ17*5)) -> 0 | BD17: =MIN(5,BC17*2) -> 0 | BE17: 0.025 | BF17: 0.025 | BH17: =MIN(3,IF(BG17/BF17<0.6,0,BG17/BF17*3)) -> 0 | BI17: =H17 -> 0 | BO17: 295.14874 | BQ17: 1.53
A18: 东莞运营中心 | B18: 惠州 | C18: 0.048 | E18: =D18/C18 -> 0 | F18: =MIN(10,IF(E18>=0.6,E18*10,0)) -> 0 | G18: 0.02 | I18: =H18/G18 -> 0 | J18: =MIN(10,IF(I18>=0.6,I18*10,0)) -> 0 | K18: 14978.287 | M18: =L18/(K18*90/365) -> 0 | N18: =L18/K18-90/365 -> -0.24657534 | O18: 5242.4004 | Q18: =MIN(15,IF(P18/O18<0.6,0,P18/O18*15)) -> 0 | R18: 911.56853 | S18: =VLOOKUP(B18,[1]自有品牌手机收入!$F$2:$G$23,2,0)/10000 -> 106.89024 | T18: =S18/(R18*90/365) -> 0.47555318 | U18: =S18/R18-90/365 -> -0.12931565 | V18: 319.04899 | W18: =S18 -> 106.89024 | X18: =MIN(15,IF(W18/V18<0.6,0,W18/V18*15)) -> 0 | Y18: 3570.5519 | Z18: =VLOOKUP(B18,'[1]自有品牌智能硬件收入（已加配额制摊分）'!$H$2:$I$23,2,0)/10000 -> 1869.8369 | AA18: =Z18/(Y18*90/365) -> 2.123825 | AB18: =Z18/Y18-90/365 -> 0.27710753 | AC18: 1249.6932 | AD18: =Z18 -> 1869.8369 | AE18: =MIN(10,IF(AD18/AC18<0.6,0,AD18/AC18*10)) -> 10 | AF18: 625.74505 | AG18: =VLOOKUP(B18,[1]非配额自有品牌智能硬件收入!$G$2:$H$23,2,0)/10000 -> 43.067067 | AH18: =AG18/(AF18*90/365) -> 0.27912467 | AI18: =AG18/AF18-90/365 -> -0.17775008 | AJ18: 219.01077 | AK18: =AG18 -> 43.067067 | AL18: =MIN(10,IF(AK18/AJ18<0.6,0,AK18/AJ18*10)) -> 0 | AM18: 待发文后录入 | AN18: 3.4836575 | AO18: 57 | AP18: 57 | AQ18: =VLOOKUP(B18,[1]渠道类指标!$B$2:$F$22,5,0) -> 113 | AR18: =AQ18/AP18 -> 1.9824561 | AS18: =MIN(8,IF(AR18>=0.8,AR18*8,0)) -> 8 | AT18: 19186.2 | AU18: 6715 | AV18: =VLOOKUP(B18,[1]渠道类指标!$B$2:$F$22,4,0) -> 7441 | AW18: =AV18/AU18 -> 1.1081162 | AX18: =MIN(8,IF(AW18>=0.8,AW18*8,0)) -> 8 | AY18: 0.52 | AZ18: 0.156 | BB18: =MIN(5,IF(BA18/AZ18<0.6,0,BA18/AZ18*5)) -> 0 | BD18: =MIN(5,BC18*2) -> 0 | BE18: 0.025 | BF18: 0.025 | BH18: =MIN(3,IF(BG18/BF18<0.6,0,BG18/BF18*3)) -> 0 | BI18: =H18 -> 0 | BO18: 319.04899 | BQ18: 1.59
A19: 东莞运营中心 | B19: 珠海 | C19: 0.048 | E19: =D19/C19 -> 0 | F19: =MIN(10,IF(E19>=0.6,E19*10,0)) -> 0 | G19: 0.02 | I19: =H19/G19 -> 0 | J19: =MIN(10,IF(I19>=0.6,I19*10,0)) -> 0 | K19: 9094.7741 | M19: =L19/(K19*90/365) -> 0 | N19: =L19/K19-90/365 -> -0.24657534 | O19: 3183.1709 | Q19: =MIN(15,IF(P19/O19<0.6,0,P19/O19*15)) -> 0 | R19: 391.49987 | S19: =VLOOKUP(B19,[1]自有品牌手机收入!$F$2:$G$23,2,0)/10000 -> 3.937701 | T19: =S19/(R19*90/365) -> 0.040790729 | U19: =S19/R19-90/365 -> -0.23651735 | V19: 137.02495 | W19: =S19 -> 3.937701 | X19: =MIN(15,IF(W19/V19<0.6,0,W19/V19*15)) -> 0 | Y19: 1974.6823 | Z19: =VLOOKUP(B19,'[1]自有品牌智能硬件收入（已加配额制摊分）'!$H$2:$I$23,2,0)/10000 -> 807.91733 | AA19: =Z19/(Y19*90/365) -> 1.6592814 | AB19: =Z19/Y19-90/365 -> 0.16256253 | AC19: 691.13882 | AD19: =Z19 -> 807.91733 | AE19: =MIN(10,IF(AD19/AC19<0.6,0,AD19/AC19*10)) -> 10 | AF19: 332.89759 | AG19: =VLOOKUP(B19,[1]非配额自有品牌智能硬件收入!$G$2:$H$23,2,0)/10000 -> 22.305259 | AH19: =AG19/(AF19*90/365) -> 0.27173587 | AI19: =AG19/AF19-90/365 -> -0.17957198 | AJ19: 116.51416 | AK19: =AG19 -> 22.305259 | AL19: =MIN(10,IF(AK19/AJ19<0.6,0,AK19/AJ19*10)) -> 0 | AM19: 待发文后录入 | AN19: 4.2564392 | AO19: 24 | AP19: 24 | AQ19: =VLOOKUP(B19,[1]渠道类指标!$B$2:$F$22,5,0) -> 28 | AR19: =AQ19/AP19 -> 1.1666667 | AS19: =MIN(8,IF(AR19>=0.8,AR19*8,0)) -> 8 | AT19: 22816.8 | AU19: 7986 | AV19: =VLOOKUP(B19,[1]渠道类指标!$B$2:$F$22,4,0) -> 8383 | AW19: =AV19/AU19 -> 1.049712 | AX19: =MIN(8,IF(AW19>=0.8,AW19*8,0)) -> 8 | AY19: 0.3 | AZ19: 0.09 | BB19: =MIN(5,IF(BA19/AZ19<0.6,0,BA19/AZ19*5)) -> 0 | BD19: =MIN(5,BC19*2) -> 0 | BE19: 0.025 | BF19: 0.025 | BH19: =MIN(3,IF(BG19/BF19<0.6,0,BG19/BF19*3)) -> 0 | BI19: =H19 -> 0 | BO19: 137.02495 | BQ19: 0.84
A20: 东莞运营中心 | B20: 河源 | C20: 0.048 | E20: =D20/C20 -> 0 | F20: =MIN(10,IF(E20>=0.6,E20*10,0)) -> 0 | G20: 0.02 | I20: =H20/G20 -> 0 | J20: =MIN(10,IF(I20>=0.6,I20*10,0)) -> 0 | K20: 5694.5599 | M20: =L20/(K20*90/365) -> 0 | N20: =L20/K20-90/365 -> -0.24657534 | O20: 1993.096 | Q20: =MIN(15,IF(P20/O20<0.6,0,P20/O20*15)) -> 0 | R20: 375.47377 | S20: =VLOOKUP(B20,[1]自有品牌手机收入!$F$2:$G$23,2,0)/10000 -> 9.006724 | T20: =S20/(R20*90/365) -> 0.097283145 | U20: =S20/R20-90/365 -> -0.22258772 | V20: 131.41582 | W20: =S20 -> 9.006724 | X20: =MIN(15,IF(W20/V20<0.6,0,W20/V20*15)) -> 0 | Y20: 1451.7612 | Z20: =VLOOKUP(B20,'[1]自有品牌智能硬件收入（已加配额制摊分）'!$H$2:$I$23,2,0)/10000 -> 197.64622 | AA20: =Z20/(Y20*90/365) -> 0.55213295 | AB20: =Z20/Y20-90/365 -> -0.11043297 | AC20: 508.11644 | AD20: =Z20 -> 197.64622 | AE20: =MIN(10,IF(AD20/AC20<0.6,0,AD20/AC20*10)) -> 0 | AF20: 230.90488 | AG20: =VLOOKUP(B20,[1]非配额自有品牌智能硬件收入!$G$2:$H$23,2,0)/10000 -> 35.831564 | AH20: =AG20/(AF20*90/365) -> 0.62933664 | AI20: =AG20/AF20-90/365 -> -0.091396446 | AJ20: 80.816707 | AK20: =AG20 -> 35.831564 | AL20: =MIN(10,IF(AK20/AJ20<0.6,0,AK20/AJ20*10)) -> 0 | AM20: 待发文后录入 | AN20: 2.7742168 | AO20: 20 | AP20: 20 | AQ20: =VLOOKUP(B20,[1]渠道类指标!$B$2:$F$22,5,0) -> 46 | AR20: =AQ20/AP20 -> 2.3 | AS20: =MIN(8,IF(AR20>=0.8,AR20*8,0)) -> 8 | AT20: 12481.65 | AU20: 4369 | AV20: =VLOOKUP(B20,[1]渠道类指标!$B$2:$F$22,4,0) -> 1779 | AW20: =AV20/AU20 -> 0.407187 | AX20: =MIN(8,IF(AW20>=0.8,AW20*8,0)) -> 0 | AY20: 0.2 | AZ20: 0.06 | BB20: =MIN(5,IF(BA20/AZ20<0.6,0,BA20/AZ20*5)) -> 0 | BD20: =MIN(5,BC20*2) -> 0 | BE20: 0.025 | BF20: 0.025 | BH20: =MIN(3,IF(BG20/BF20<0.6,0,BG20/BF20*3)) -> 0 | BI20: =H20 -> 0 | BO20: 131.41582 | BQ20: 0.55
A21: 东莞运营中心 | B21: 合计3 | C21: 0.048 | E21: =D21/C21 -> 0 | F21: =MIN(10,IF(E21>=0.6,E21*10,0)) -> 0 | G21: 0.02 | I21: =H21/G21 -> 0 | J21: =MIN(10,IF(I21>=0.6,I21*10,0)) -> 0 | K21: =SUM(K16:K20) -> 117342.68 | M21: =L21/(K21*90/365) -> 0 | N21: =L21/K21-90/365 -> -0.24657534 | O21: =SUM(O16:O20) -> 41069.936 | Q21: =SUM(Q16:Q20) -> 0 | R21: 3737.263 | S21: =SUM(S16:S20) -> 168.95194 | T21: =S21/(R21*90/365) -> 0.18334112 | U21: =S21/R21-90/365 -> -0.20136794 | V21: 1308.042 | W21: =S21 -> 168.95194 | X21: =MIN(15,IF(W21/V21<0.6,0,W21/V21*15)) -> 0 | Y21: =SUM(Y16:Y20) -> 16253.628 | Z21: =SUM(Z16:Z20) -> 5919.8576 | AA21: =Z21/(Y21*90/365) -> 1.4771048 | AB21: =Z21/Y21-90/365 -> 0.11764227 | AC21: =SUM(AC16:AC20) -> 5688.7699 | AD21: =Z21 -> 5919.8576 | AE21: =MIN(10,IF(AD21/AC21<0.6,0,AD21/AC21*10)) -> 10 | AF21: =SUM(AF16:AF20) -> 2907.4004 | AG21: =SUM(AG16:AG20) -> 117.70909 | AH21: =AG21/(AF21*90/365) -> 0.16419332 | AI21: =AG21/AF21-90/365 -> -0.20608932 | AJ21: =SUM(AJ16:AJ20) -> 1017.5901 | AK21: =AG21 -> 117.70909 | AL21: =MIN(10,IF(AK21/AJ21<0.6,0,AK21/AJ21*10)) -> 0 | AM21: 待发文后录入 | AN21: =SUM(AN16:AN20) -> 15.087526 | AO21: =SUM(AO16:AO20) -> 173 | AP21: =SUM(AP16:AP20) -> 173 | AQ21: =SUM(AQ16:AQ20) -> 357 | AR21: =AQ21/AP21 -> 2.0635838 | AS21: =MIN(8,IF(AR21>=0.8,AR21*8,0)) -> 8 | AT21: =SUM(AT16:AT20) -> 254955.37 | AU21: =SUM(AU16:AU20) -> 89235 | AV21: =SUM(AV16:AV20) -> 35029 | AW21: =AV21/AU21 -> 0.39254777 | AX21: =MIN(8,IF(AW21>=0.8,AW21*8,0)) -> 0 | AY21: =SUM(AY16:AY20) -> 2.42 | AZ21: =SUM(AZ16:AZ20) -> 0.726 | BB21: =MIN(5,IF(BA21/AZ21<0.6,0,BA21/AZ21*5)) -> 0 | BD21: =MIN(5,BC21*2) -> 0 | BE21: 0.025 | BF21: 0.025 | BH21: =MIN(3,IF(BG21/BF21<0.6,0,BG21/BF21*3)) -> 0 | BI21: =H21 -> 0 | BO21: 1308.042 | BQ21: =SUM(BQ16:BQ20) -> 7.56
A22: 佛山运营中心 | B22: 佛山 | C22: 0.048 | E22: =D22/C22 -> 0 | F22: =MIN(10,IF(E22>=0.6,E22*10,0)) -> 0 | G22: 0.02 | I22: =H22/G22 -> 0 | J22: =MIN(10,IF(I22>=0.6,I22*10,0)) -> 0 | K22: 33618.386 | M22: =L22/(K22*90/365) -> 0 | N22: =L22/K22-90/365 -> -0.24657534 | O22: 11766.435 | Q22: =MIN(15,IF(P22/O22<0.6,0,P22/O22*15)) -> 0 | R22: 902.06423 | S22: =VLOOKUP(B22,[1]自有品牌手机收入!$F$2:$G$23,2,0)/10000 -> 35.694675 | T22: =S22/(R22*90/365) -> 0.1604783 | U22: =S22/R22-90/365 -> -0.20700535 | V22: 315.72248 | W22: =S22 -> 35.694675 | X22: =MIN(15,IF(W22/V22<0.6,0,W22/V22*15)) -> 0 | Y22: 5228.8938 | Z22: =VLOOKUP(B22,'[1]自有品牌智能硬件收入（已加配额制摊分）'!$H$2:$I$23,2,0)/10000 -> 1845.1953 | AA22: =Z22/(Y22*90/365) -> 1.4311425 | AB22: =Z22/Y22-90/365 -> 0.10630911 | AC22: 1830.1128 | AD22: =Z22 -> 1845.1953 | AE22: =MIN(10,IF(AD22/AC22<0.6,0,AD22/AC22*10)) -> 10 | AF22: 914.58992 | AG22: =VLOOKUP(B22,[1]非配额自有品牌智能硬件收入!$G$2:$H$23,2,0)/10000 -> 2.787544 | AH22: =AG22/(AF22*90/365) -> 0.012360774 | AI22: =AG22/AF22-90/365 -> -0.24352748 | AJ22: 320.10647 | AK22: =AG22 -> 2.787544 | AL22: =MIN(10,IF(AK22/AJ22<0.6,0,AK22/AJ22*10)) -> 0 | AM22: 待发文后录入 | AN22: 3.3571429 | AO22: 23 | AP22: 23 | AQ22: =VLOOKUP(B22,[1]渠道类指标!$B$2:$F$22,5,0) -> 38 | AR22: =AQ22/AP22 -> 1.6521739 | AS22: =MIN(8,IF(AR22>=0.8,AR22*8,0)) -> 8 | AT22: 40333.7 | AU22: 14117 | AV22: =VLOOKUP(B22,[1]渠道类指标!$B$2:$F$22,4,0) -> 24049 | AW22: =AV22/AU22 -> 1.7035489 | AX22: =MIN(8,IF(AW22>=0.8,AW22*8,0)) -> 8 | AY22: 0.76 | AZ22: 0.228 | BB22: =MIN(5,IF(BA22/AZ22<0.6,0,BA22/AZ22*5)) -> 0 | BD22: =MIN(5,BC22*2) -> 0 | BE22: 0.025 | BF22: 0.025 | BH22: =MIN(3,IF(BG22/BF22<0.6,0,BG22/BF22*3)) -> 0 | BI22: =H22 -> 0 | BO22: 315.72248 | BQ22: 2.32
A23: 佛山运营中心 | B23: 江门 | C23: 0.048 | E23: =D23/C23 -> 0 | F23: =MIN(10,IF(E23>=0.6,E23*10,0)) -> 0 | G23: 0.02 | I23: =H23/G23 -> 0 | J23: =MIN(10,IF(I23>=0.6,I23*10,0)) -> 0 | K23: 9522.5825 | M23: =L23/(K23*90/365) -> 0 | N23: =L23/K23-90/365 -> -0.24657534 | O23: 3332.9039 | Q23: =MIN(15,IF(P23/O23<0.6,0,P23/O23*15)) -> 0 | R23: 453.74866 | S23: =VLOOKUP(B23,[1]自有品牌手机收入!$F$2:$G$23,2,0)/10000 -> 47.967176 | T23: =S23/(R23*90/365) -> 0.42872534 | U23: =S23/R23-90/365 -> -0.14086225 | V23: 158.81203 | W23: =S23 -> 47.967176 | X23: =MIN(15,IF(W23/V23<0.6,0,W23/V23*15)) -> 0 | Y23: 3540.346 | Z23: =VLOOKUP(B23,'[1]自有品牌智能硬件收入（已加配额制摊分）'!$H$2:$I$23,2,0)/10000 -> 1736.5674 | AA23: =Z23/(Y23*90/365) -> 1.9892817 | AB23: =Z23/Y23-90/365 -> 0.24393248 | AC23: 1239.1211 | AD23: =Z23 -> 1736.5674 | AE23: =MIN(10,IF(AD23/AC23<0.6,0,AD23/AC23*10)) -> 10 | AF23: 577.51985 | AG23: =VLOOKUP(B23,[1]非配额自有品牌智能硬件收入!$G$2:$H$23,2,0)/10000 -> 139.06794 | AH23: =AG23/(AF23*90/365) -> 0.9765859 | AI23: =AG23/AF23-90/365 -> -0.0057733397 | AJ23: 202.13195 | AK23: =AG23 -> 139.06794 | AL23: =MIN(10,IF(AK23/AJ23<0.6,0,AK23/AJ23*10)) -> 6.8800572 | AM23: 待发文后录入 | AN23: 4.074058 | AO23: 24 | AP23: 24 | AQ23: =VLOOKUP(B23,[1]渠道类指标!$B$2:$F$22,5,0) -> 30 | AR23: =AQ23/AP23 -> 1.25 | AS23: =MIN(8,IF(AR23>=0.8,AR23*8,0)) -> 8 | AT23: 14681.457 | AU23: 5139 | AV23: =VLOOKUP(B23,[1]渠道类指标!$B$2:$F$22,4,0) -> 5178 | AW23: =AV23/AU23 -> 1.007589 | AX23: =MIN(8,IF(AW23>=0.8,AW23*8,0)) -> 8 | AY23: 1.6 | AZ23: 0.48 | BB23: =MIN(5,IF(BA23/AZ23<0.6,0,BA23/AZ23*5)) -> 0 | BD23: =MIN(5,BC23*2) -> 0 | BE23: 0.025 | BF23: 0.025 | BH23: =MIN(3,IF(BG23/BF23<0.6,0,BG23/BF23*3)) -> 0 | BI23: =H23 -> 0 | BO23: 158.81203 | BQ23: 1.35
A24: 佛山运营中心 | B24: 湛江 | C24: 0.048 | E24: =D24/C24 -> 0 | F24: =MIN(10,IF(E24>=0.6,E24*10,0)) -> 0 | G24: 0.02 | I24: =H24/G24 -> 0 | J24: =MIN(10,IF(I24>=0.6,I24*10,0)) -> 0 | K24: 11793.204 | M24: =L24/(K24*90/365) -> 0 | N24: =L24/K24-90/365 -> -0.24657534 | O24: 4127.6214 | Q24: =MIN(15,IF(P24/O24<0.6,0,P24/O24*15)) -> 0 | R24: 1184.4022 | S24: =VLOOKUP(B24,[1]自有品牌手机收入!$F$2:$G$23,2,0)/10000 -> 10.582606 | T24: =S24/(R24*90/365) -> 0.036236293 | U24: =S24/R24-90/365 -> -0.23764037 | V24: 414.54078 | W24: =S24 -> 10.582606 | X24: =MIN(15,IF(W24/V24<0.6,0,W24/V24*15)) -> 0 | Y24: 3604.7726 | Z24: =VLOOKUP(B24,'[1]自有品牌智能硬件收入（已加配额制摊分）'!$H$2:$I$23,2,0)/10000 -> 2323.1478 | AA24: =Z24/(Y24*90/365) -> 2.6136614 | AB24: =Z24/Y24-90/365 -> 0.3978891 | AC24: 1261.6704 | AD24: =Z24 -> 2323.1478 | AE24: =MIN(10,IF(AD24/AC24<0.6,0,AD24/AC24*10)) -> 10 | AF24: 593.22231 | AG24: =VLOOKUP(B24,[1]非配额自有品牌智能硬件收入!$G$2:$H$23,2,0)/10000 -> 100.86762 | AH24: =AG24/(AF24*90/365) -> 0.68957997 | AI24: =AG24/AF24-90/365 -> -0.076541925 | AJ24: 207.62781 | AK24: =AG24 -> 100.86762 | AL24: =MIN(10,IF(AK24/AJ24<0.6,0,AK24/AJ24*10)) -> 0 | AM24: 待发文后录入 | AN24: 2.1455224 | AO24: 20 | AP24: 20 | AQ24: =VLOOKUP(B24,[1]渠道类指标!$B$2:$F$22,5,0) -> 33 | AR24: =AQ24/AP24 -> 1.65 | AS24: =MIN(8,IF(AR24>=0.8,AR24*8,0)) -> 8 | AT24: 22812.679 | AU24: 7984 | AV24: =VLOOKUP(B24,[1]渠道类指标!$B$2:$F$22,4,0) -> 3066 | AW24: =AV24/AU24 -> 0.38401804 | AX24: =MIN(8,IF(AW24>=0.8,AW24*8,0)) -> 0 | AY24: 0.26 | AZ24: 0.078 | BB24: =MIN(5,IF(BA24/AZ24<0.6,0,BA24/AZ24*5)) -> 0 | BD24: =MIN(5,BC24*2) -> 0 | BE24: 0.025 | BF24: 0.025 | BH24: =MIN(3,IF(BG24/BF24<0.6,0,BG24/BF24*3)) -> 0 | BI24: =H24 -> 0 | BO24: 414.54078 | BQ24: 1.43
A25: 佛山运营中心 | B25: 茂名 | C25: 0.048 | E25: =D25/C25 -> 0 | F25: =MIN(10,IF(E25>=0.6,E25*10,0)) -> 0 | G25: 0.02 | I25: =H25/G25 -> 0 | J25: =MIN(10,IF(I25>=0.6,I25*10,0)) -> 0 | K25: 8814.2258 | M25: =L25/(K25*90/365) -> 0 | N25: =L25/K25-90/365 -> -0.24657534 | O25: 3084.979 | Q25: =MIN(15,IF(P25/O25<0.6,0,P25/O25*15)) -> 0 | R25: 497.97423 | S25: =VLOOKUP(B25,[1]自有品牌手机收入!$F$2:$G$23,2,0)/10000 -> 132.76502 | T25: =S25/(R25*90/365) -> 1.0812525 | U25: =S25/R25-90/365 -> 0.020034875 | V25: 174.29098 | W25: =S25 -> 132.76502 | X25: =MIN(15,IF(W25/V25<0.6,0,W25/V25*15)) -> 11.426152 | Y25: 2423.9824 | Z25: =VLOOKUP(B25,'[1]自有品牌智能硬件收入（已加配额制摊分）'!$H$2:$I$23,2,0)/10000 -> 1673.691 | AA25: =Z25/(Y25*90/365) -> 2.8002459 | AB25: =Z25/Y25-90/365 -> 0.44389625 | AC25: 848.39385 | AD25: =Z25 -> 1673.691 | AE25: =MIN(10,IF(AD25/AC25<0.6,0,AD25/AC25*10)) -> 10 | AF25: 383.65154 | AG25: =VLOOKUP(B25,[1]非配额自有品牌智能硬件收入!$G$2:$H$23,2,0)/10000 -> 5.002331 | AH25: =AG25/(AF25*90/365) -> 0.052879316 | AI25: =AG25/AF25-90/365 -> -0.23353661 | AJ25: 134.27804 | AK25: =AG25 -> 5.002331 | AL25: =MIN(10,IF(AK25/AJ25<0.6,0,AK25/AJ25*10)) -> 0 | AM25: 待发文后录入 | AN25: 5.6020727 | AO25: 10 | AP25: 10 | AQ25: =VLOOKUP(B25,[1]渠道类指标!$B$2:$F$22,5,0) -> 12 | AR25: =AQ25/AP25 -> 1.2 | AS25: =MIN(8,IF(AR25>=0.8,AR25*8,0)) -> 8 | AT25: 8374.6 | AU25: 2931 | AV25: =VLOOKUP(B25,[1]渠道类指标!$B$2:$F$22,4,0) -> 5151 | AW25: =AV25/AU25 -> 1.7574207 | AX25: =MIN(8,IF(AW25>=0.8,AW25*8,0)) -> 8 | AY25: 0.32 | AZ25: 0.096 | BB25: =MIN(5,IF(BA25/AZ25<0.6,0,BA25/AZ25*5)) -> 0 | BD25: =MIN(5,BC25*2) -> 0 | BE25: 0.025 | BF25: 0.025 | BH25: =MIN(3,IF(BG25/BF25<0.6,0,BG25/BF25*3)) -> 0 | BI25: =H25 -> 0 | BO25: 174.29098 | BQ25: 0.89
A26: 佛山运营中心 | B26: 阳江 | C26: 0.048 | E26: =D26/C26 -> 0 | F26: =MIN(10,IF(E26>=0.6,E26*10,0)) -> 0 | G26: 0.02 | I26: =H26/G26 -> 0 | J26: =MIN(10,IF(I26>=0.6,I26*10,0)) -> 0 | K26: 4812.7812 | M26: =L26/(K26*90/365) -> 0 | N26: =L26/K26-90/365 -> -0.24657534 | O26: 1684.4734 | Q26: =MIN(15,IF(P26/O26<0.6,0,P26/O26*15)) -> 0 | R26: 508.91439 | S26: =VLOOKUP(B26,[1]自有品牌手机收入!$F$2:$G$23,2,0)/10000 -> 127.63379 | T26: =S26/(R26*90/365) -> 1.0171179 | U26: =S26/R26-90/365 -> 0.0042208483 | V26: 178.12004 | W26: =S26 -> 127.63379 | X26: =MIN(15,IF(W26/V26<0.6,0,W26/V26*15)) -> 10.748408 | Y26: 1488.5746 | Z26: =VLOOKUP(B26,'[1]自有品牌智能硬件收入（已加配额制摊分）'!$H$2:$I$23,2,0)/10000 -> 599.13646 | AA26: =Z26/(Y26*90/365) -> 1.6323208 | AB26: =Z26/Y26-90/365 -> 0.15591471 | AC26: 521.0011 | AD26: =Z26 -> 599.13646 | AE26: =MIN(10,IF(AD26/AC26<0.6,0,AD26/AC26*10)) -> 10 | AF26: 233.79363 | AG26: =VLOOKUP(B26,[1]非配额自有品牌智能硬件收入!$G$2:$H$23,2,0)/10000 -> 3.196806 | AH26: =AG26/(AF26*90/365) -> 0.05545414 | AI26: =AG26/AF26-90/365 -> -0.23290172 | AJ26: 81.827769 | AK26: =AG26 -> 3.196806 | AL26: =MIN(10,IF(AK26/AJ26<0.6,0,AK26/AJ26*10)) -> 0 | AM26: 待发文后录入 | AN26: 5.9085624 | AO26: 16 | AP26: 16 | AQ26: =VLOOKUP(B26,[1]渠道类指标!$B$2:$F$22,5,0) -> 19 | AR26: =AQ26/AP26 -> 1.1875 | AS26: =MIN(8,IF(AR26>=0.8,AR26*8,0)) -> 8 | AT26: 8260.824 | AU26: 2891 | AV26: =VLOOKUP(B26,[1]渠道类指标!$B$2:$F$22,4,0) -> 1886 | AW26: =AV26/AU26 -> 0.65236942 | AX26: =MIN(8,IF(AW26>=0.8,AW26*8,0)) -> 0 | AY26: 0.26 | AZ26: 0.078 | BB26: =MIN(5,IF(BA26/AZ26<0.6,0,BA26/AZ26*5)) -> 0 | BD26: =MIN(5,BC26*2) -> 0 | BE26: 0.025 | BF26: 0.025 | BH26: =MIN(3,IF(BG26/BF26<0.6,0,BG26/BF26*3)) -> 0 | BI26: =H26 -> 0 | BO26: 178.12004 | BQ26: 0.51
A27: 佛山运营中心 | B27: 合计4 | C27: 0.048 | E27: =D27/C27 -> 0 | F27: =MIN(10,IF(E27>=0.6,E27*10,0)) -> 0 | G27: 0.02 | I27: =H27/G27 -> 0 | J27: =MIN(10,IF(I27>=0.6,I27*10,0)) -> 0 | K27: =SUM(K22:K26) -> 68561.18 | M27: =L27/(K27*90/365) -> 0 | N27: =L27/K27-90/365 -> -0.24657534 | O27: =SUM(O22:O26) -> 23996.413 | Q27: =SUM(Q22:Q26) -> 0 | R27: 3547.1037 | S27: =SUM(S22:S26) -> 354.64326 | T27: =S27/(R27*90/365) -> 0.40547883 | U27: =S27/R27-90/365 -> -0.14659426 | V27: 1241.4863 | W27: =S27 -> 354.64326 | X27: =MIN(15,IF(W27/V27<0.6,0,W27/V27*15)) -> 0 | Y27: =SUM(Y22:Y26) -> 16286.569 | Z27: =SUM(Z22:Z26) -> 8177.7379 | AA27: =Z27/(Y27*90/365) -> 2.0363571 | AB27: =Z27/Y27-90/365 -> 0.2555401 | AC27: =SUM(AC22:AC26) -> 5700.2993 | AD27: =Z27 -> 8177.7379 | AE27: =MIN(10,IF(AD27/AC27<0.6,0,AD27/AC27*10)) -> 10 | AF27: =SUM(AF22:AF26) -> 2702.7772 | AG27: =SUM(AG22:AG26) -> 250.92223 | AH27: =AG27/(AF27*90/365) -> 0.37651237 | AI27: =AG27/AF27-90/365 -> -0.15373668 | AJ27: =SUM(AJ22:AJ26) -> 945.97203 | AK27: =AG27 -> 250.92223 | AL27: =MIN(10,IF(AK27/AJ27<0.6,0,AK27/AJ27*10)) -> 0 | AM27: 待发文后录入 | AN27: =SUM(AN22:AN26) -> 21.087358 | AO27: =SUM(AO22:AO26) -> 93 | AP27: =SUM(AP22:AP26) -> 93 | AQ27: =SUM(AQ22:AQ26) -> 132 | AR27: =AQ27/AP27 -> 1.4193548 | AS27: =MIN(8,IF(AR27>=0.8,AR27*8,0)) -> 8 | AT27: =SUM(AT22:AT26) -> 94463.26 | AU27: =SUM(AU22:AU26) -> 33062 | AV27: =SUM(AV22:AV26) -> 39330 | AW27: =AV27/AU27 -> 1.1895832 | AX27: =MIN(8,IF(AW27>=0.8,AW27*8,0)) -> 8 | AY27: =SUM(AY22:AY26) -> 3.2 | AZ27: =SUM(AZ22:AZ26) -> 0.96 | BB27: =MIN(5,IF(BA27/AZ27<0.6,0,BA27/AZ27*5)) -> 0 | BD27: =MIN(5,BC27*2) -> 0 | BE27: 0.025 | BF27: 0.025 | BH27: =MIN(3,IF(BG27/BF27<0.6,0,BG27/BF27*3)) -> 0 | BI27: =H27 -> 0 | BO27: 1241.4863 | BQ27: =SUM(BQ22:BQ26) -> 6.5
A28: 全省 | B28: 全省合计 | C28: 0.04 | E28: =D28/C28 -> 0 | F28: =MIN(10,IF(E28>=0.6,E28*10,0)) -> 0 | G28: 0.02 | I28: =H28/G28 -> 0 | J28: =MIN(10,IF(I28>=0.6,I28*10,0)) -> 0 | K28: =K27+K21+K15+K8 -> 501115 | M28: =L28/(K28*90/365) -> 0 | N28: =L28/K28-90/365 -> -0.24657534 | Q28: =Q27+Q21+Q15+Q8 -> 0 | R28: =R27+R21+R15+R8 -> 15000 | S28: =S8+S15+S21+S27 -> 1570.8648 | T28: =S28/(R28*90/365) -> 0.42471529 | U28: =S28/R28-90/365 -> -0.14185103 | V28: 5250 | W28: =S28 -> 1570.8648 | X28: =X27+X21+X15+X8 -> 0 | Y28: =Y27+Y21+Y15+Y8 -> 67351.9 | Z28: =Z8+Z15+Z21+Z27 -> 30874.8 | AA28: =Z28/(Y28*90/365) -> 1.8591082 | AB28: =Z28/Y28-90/365 -> 0.21183489 | AC28: =AC27+AC21+AC15+AC8 -> 23573.165 | AD28: =Z28 -> 30874.8 | AE28: =AE27+AE21+AE15+AE8 -> 40 | AF28: =AF27+AF21+AF15+AF8 -> 11768.1 | AG28: =AG27+AG21+AG15+AG8 -> 995.06518 | AH28: =AG28/(AF28*90/365) -> 0.34292215 | AI28: =AG28/AF28-90/365 -> -0.1620192 | AJ28: =AJ27+AJ21+AJ15+AJ8 -> 4118.835 | AK28: =AG28 -> 995.06518 | AL28: =AL27+AL21+AL15+AL8 -> 0 | AN28: =AN27+AN21+AN15+AN8 -> 72.058822 | AO28: =AO27+AO21+AO15+AO8 -> 551 | AP28: =AP27+AP21+AP15+AP8 -> 551 | AQ28: =AQ27+AQ21+AQ15+AQ8 -> 829 | AR28: =AQ28/AP28 -> 1.5045372 | AS28: =MIN(8,IF(AR28>=0.8,AR28*8,0)) -> 8 | AT28: =AT27+AT21+AT15+AT8 -> 780297.53 | AU28: =AU27+AU21+AU15+AU8 -> 273105 | AV28: =AV27+AV21+AV15+AV8 -> 123875 | AW28: =AV28/AU28 -> 0.45358012 | AX28: =MIN(8,IF(AW28>=0.8,AW28*8,0)) -> 0 | AY28: =AY27+AY21+AY15+AY8 -> 12.24 | AZ28: =AZ27+AZ21+AZ15+AZ8 -> 3.672 | BB28: =MIN(5,IF(BA28/AZ28<0.6,0,BA28/AZ28*5)) -> 0 | BD28: =MIN(5,BC28*2) -> 0 | BE28: 0.025 | BF28: 0.025 | BH28: =MIN(3,IF(BG28/BF28<0.6,0,BG28/BF28*3)) -> 0 | BI28: =H28 -> 0 | BO28: 5250 | BQ28: =BQ27+BQ21+BQ15+BQ8 -> 29.99
A29: 分值 | B29: 分值 | F29: 10 | J29: 10 | Q29: 15 | X29: 15 | AE29: 10 | AL29: 10 | AN29: 9 | AS29: 8 | AX29: 8 | BB29: 5 | BD29: 5 | BH29: 3 | BJ29: 5 | BL29: 2 | BM29: -10
