Workbook

Sheet 2019地市KPI导入模板
A1: 考核对象 | C1: 利润类指标（20分） | K1: 规模类指标（50分） | AM1: 重点产品指标（9分） | AO1: 渠道质量指标（16分） | AY1: 铁通指标（5分） | BC1: 加减分类 | BN1: kpi直接总分（加总） | BO1: 重点系数 | BT1: 考虑重点系数后的KPI总分（最终考核得分是=1-14项得分*70%+1-14项得分*30%*完成率）
A2: 运营中心 | B2: 地市 | C2: 直接毛利率-2季度指标 | D2: 直接毛利率-完成 | E2: 直接毛利率-完成比率 | F2: 直接毛利率-得分 | G2: 直接净利率-2季度指标 | H2: 直接净利率-完成 | I2: 直接净利率-完成比率 | J2: 直接净利率-得分 | K2: 二季度基本目标 | L2: 运营收入-1-3月累计完成 | M2: 完成（万元） | N2: 运营收入-时间进度 | O2: 运营收入-2季度指标（万元） | P2: 运营收入-完成（万元） | Q2: 得分 | R2: 自有品牌手机收入-全年指标 （万元） | S2: 自有品牌手机收入-1-3月累计完成 | T2: 自有品牌手机收入-时间进度完成率 | U2: 自有品牌手机收入-时间进度 | V2: 2季度指标（万元） | W2: 完成（万元） | X2: 得分 | Y2: 自有品牌智能硬件收入-全年指标（万元） | Z2: 自有品牌智能硬件收入-1-3月累计完成 | AA2: 自有品牌智能硬件收入-时间进度完成率 | AB2: 自有品牌智能硬件收入-时间进度 | AC2: 2季度基本目标 | AD2: 完成（万元） | AE2: 得分 | AF2: 非集团集采类别自有品牌智能硬件收入-全年指标（万元） | AG2: 2019年第2季度 家庭智能硬件销售收入 （万元） | AH2: 完成（万元） | AI2: 得分 | AJ2: 二季度基本目标 | AK2: 完成（万元） | AL2: 得分 | AM2: 重点产品 | AN2: 重点产品得分 | AO2: 优质客户目标值-全年目标值（个） | AP2: 优质客户目标值-2季度指标 | AQ2: 优质客户目标值-2季度完成 | AR2: 优质客户目标值-2季度完成率 | AS2: 优质客户2季度得分 | AT2: KA客户手机销量目标值-全年目标值（台） | AU2: 2季度指标 | AV2: KA客户手机销量目标值-1季度完成 | AW2: 2季度完成率 | AX2: 2季度得分 | AY2: 铁通终端销量-全年（万台） | AZ2: 2季度铁通终端销量指标（万台） | BA2: 2季度完成率 | BB2: 2季度得分 | BC2: 新零售厅店建设-厅店（个） | BD2: 新零售厅店建设-得分 | BE2: 售后净利率- 年度指标 | BF2: 售后净利率-2季度指标 | BG2: 售后净利率-2季度完成 | BH2: 售后净利率-2季度得分 | BI2: 直接净利率-值 | BJ2: 直接净利率-1季度得分 | BK2: 三个月以上应收账款占比-值 | BL2: 三个月以上应收账款占比-2季度得分 | BM2: 重大事项扣分项-值 | BN2: kpi直接总分（加总）-值 | BO2: 1季度重点系数A（权重50%):自主品牌手机收入指标/万元-值 | BP2: 2季度重点系数A完成率 | BQ2: 1季度重点系数B（权重50%):智能音箱发展目标/万台-值 | BR2: 2季度重点系数B完成率 | BS2: 系数B完成值 | BT2: 考虑重点系数后的KPI总分（最终考核得分是=1-14项得分*70%+1-14项得分*30%*完成率）
A3: 广州运营中心 | B3: 广州 | C3: 0.048 | D3: =VLOOKUP(B3,'[2]2019年2季度虚拟核算'!C:Q,15,0) -> 0.12132318 | E3: =D3/C3 -> 2.5275663 | F3: =MIN(10,IF(E3>=0.6,E3*10,0)) -> 10 | G3: 0.02 | H3: =VLOOKUP(B3,'[2]2019年2季度虚拟核算'!C:R,16,0) -> 0.036741633 | I3: =H3/G3 -> 1.8370817 | J3: =MIN(10,IF(I3>=0.6,I3*10,0)) -> 10 | K3: 30475.94 | M3: 9527.5587 | N3: =L3/K3-90/365 -> -0.24657534 | O3: 30475.94 | Q3: 0 | R3: 1711.0482 | S3: =VLOOKUP(B3,[1]自有品牌手机收入!$F$2:$G$23,2,0)/10000 -> 50.968754 | T3: =S3/(R3*90/365) -> 0.120807 | U3: =S3/R3-90/365 -> -0.21678731 | V3: 427.76206 | W3: 90.314794 | X3: 0 | Y3: 8495.1577 | Z3: =VLOOKUP(B3,'[1]自有品牌智能硬件收入（已加配额制摊分）'!$H$2:$I$23,2,0)/10000 -> 3507.9184 | AA3: =Z3/(Y3*90/365) -> 1.6746667 | AB3: =Z3/Y3-90/365 -> 0.16635618 | AC3: 1589.1393 | AD3: 1683.7709 | AE3: 10.353995 | AF3: 1665.3 | AG3: 128.91667 | AH3: 0.63902655 | AI3: 0 | AJ3: 582.855 | AK3: 26.607965 | AL3: 0 | AM3: 待发文后录入 | AN3: 0.27777778 | AO3: 71 | AP3: 71 | AQ3: =VLOOKUP(B3,[1]渠道类指标!$B$2:$F$22,5,0) -> 77 | AR3: 1.056338 | AS3: 8 | AT3: 116549.32 | AU3: 29137.329 | AV3: =VLOOKUP(B3,[1]渠道类指标!$B$2:$F$22,4,0) -> 4553 | AW3: 0.13758982 | AX3: 0 | AY3: 2.58 | AZ3: 1.0539216 | BA3: 0.4069 | BB3: 0 | BD3: =MIN(5,BC3*2) -> 0 | BE3: 0.025 | BF3: 0.025 | BG3: 6.99 | BH3: 3 | BI3: =H3 -> 0.036741633 | BL3: -2 | BN3: 39.631772 | BO3: 598.86689 | BP3: 1.5 | BQ3: 4.69 | BR3: 0.0015349223 | BS3: 0.0015349223 | BT3: 36.668514
A4: 广州运营中心 | B4: 肇庆 | C4: 0.048 | D4: =VLOOKUP(B4,'[2]2019年2季度虚拟核算'!C:Q,15,0) -> 0.092589773 | E4: =D4/C4 -> 1.9289536 | F4: =MIN(10,IF(E4>=0.6,E4*10,0)) -> 10 | G4: 0.02 | H4: =VLOOKUP(B4,'[2]2019年2季度虚拟核算'!C:R,16,0) -> 0.03831445 | I4: =H4/G4 -> 1.9157225 | J4: =MIN(10,IF(I4>=0.6,I4*10,0)) -> 10 | K4: 838.8189 | M4: 1387.1829 | N4: =L4/K4-90/365 -> -0.24657534 | O4: 838.8189 | Q4: 16.933652 | R4: 549.92574 | S4: =VLOOKUP(B4,[1]自有品牌手机收入!$F$2:$G$23,2,0)/10000 -> 131.23382 | T4: =S4/(R4*90/365) -> 0.96781437 | U4: =S4/R4-90/365 -> -0.0079361835 | V4: 137.48143 | W4: 8.002298 | X4: 0 | Y4: 2027.8359 | Z4: =VLOOKUP(B4,'[1]自有品牌智能硬件收入（已加配额制摊分）'!$H$2:$I$23,2,0)/10000 -> 1185.2881 | AA4: =Z4/(Y4*90/365) -> 2.3705083 | AB4: =Z4/Y4-90/365 -> 0.33793354 | AC4: 31.369913 | AD4: 13.896372 | AE4: 0 | AF4: 314.88293 | AG4: 23.610417 | AH4: 13.896372 | AI4: 0 | AJ4: 110.20902 | AK4: 15.731593 | AL4: 3.3314941 | AM4: 待发文后录入 | AN4: 1.8950163 | AO4: 10 | AP4: 10 | AQ4: =VLOOKUP(B4,[1]渠道类指标!$B$2:$F$22,5,0) -> 10 | AR4: 0.8 | AS4: 6.4 | AT4: 18306.402 | AU4: 4576.6004 | AV4: =VLOOKUP(B4,[1]渠道类指标!$B$2:$F$22,4,0) -> 2509 | AW4: 0.14115281 | AX4: 0 | AY4: 0.3 | AZ4: 0.12254902 | BA4: 0.1406 | BB4: 5 | BD4: =MIN(5,BC4*2) -> 0 | BE4: 0.025 | BF4: 0.025 | BG4: 28.895608 | BH4: 3 | BI4: =H4 -> 0.03831445 | BL4: 1.17 | BN4: 57.730163 | BO4: 192.47401 | BP4: 1.5 | BQ4: 0.73 | BR4: 0.17652747 | BS4: 0.17652747 | BT4: 54.929045
A5: 广州运营中心 | B5: 清远 | C5: 0.048 | D5: =VLOOKUP(B5,'[2]2019年2季度虚拟核算'!C:Q,15,0) -> 0.087499425 | E5: =D5/C5 -> 1.8229047 | F5: =MIN(10,IF(E5>=0.6,E5*10,0)) -> 10 | G5: 0.02 | H5: =VLOOKUP(B5,'[2]2019年2季度虚拟核算'!C:R,16,0) -> 0.049465938 | I5: =H5/G5 -> 2.4732969 | J5: =MIN(10,IF(I5>=0.6,I5*10,0)) -> 10 | K5: 282.49424 | M5: 2026.1455 | N5: =L5/K5-90/365 -> -0.24657534 | O5: 282.49424 | Q5: 20.70978 | R5: 915.72739 | S5: =VLOOKUP(B5,[1]自有品牌手机收入!$F$2:$G$23,2,0)/10000 -> 177.14636 | T5: =S5/(R5*90/365) -> 0.78454234 | U5: =S5/R5-90/365 -> -0.053126546 | V5: 228.93185 | W5: 263.6998 | X5: 13 | Y5: 2256.4863 | Z5: =VLOOKUP(B5,'[1]自有品牌智能硬件收入（已加配额制摊分）'!$H$2:$I$23,2,0)/10000 -> 986.66957 | AA5: =Z5/(Y5*90/365) -> 1.7733293 | AB5: =Z5/Y5-90/365 -> 0.19068394 | AC5: 367.22221 | AD5: 145.59809 | AE5: 0 | AF5: 358.61075 | AG5: 26.147917 | AH5: 2.5700885 | AI5: 0 | AJ5: 125.51376 | AK5: 12.379558 | AL5: 0 | AM5: 待发文后录入 | AN5: 2.8207405 | AO5: 10 | AP5: 10 | AQ5: =VLOOKUP(B5,[1]渠道类指标!$B$2:$F$22,5,0) -> 18 | AR5: 1.6 | AS5: 8 | AT5: 16059.12 | AU5: 4014.78 | AV5: =VLOOKUP(B5,[1]渠道类指标!$B$2:$F$22,4,0) -> 2075 | AW5: 0.91237876 | AX5: 7.2990301 | AY5: 0.26 | AZ5: 0.10620915 | BA5: 0.1185 | BB5: 5 | BD5: =MIN(5,BC5*2) -> 0 | BE5: 0.025 | BF5: 0.025 | BG5: 5.3076767 | BH5: 3 | BI5: =H5 -> 0.049465938 | BL5: 0 | BN5: 79.829551 | BO5: 320.50459 | BP5: 1.5 | BQ5: 0.83 | BR5: 0.028667166 | BS5: 0.028667166 | BT5: 74.185608
A6: 广州运营中心 | B6: 韶关 | C6: 0.048 | D6: =VLOOKUP(B6,'[2]2019年2季度虚拟核算'!C:Q,15,0) -> 0.099634393 | E6: =D6/C6 -> 2.0757165 | F6: =MIN(10,IF(E6>=0.6,E6*10,0)) -> 10 | G6: 0.02 | H6: =VLOOKUP(B6,'[2]2019年2季度虚拟核算'!C:R,16,0) -> -0.0096546407 | I6: =H6/G6 -> -0.48273204 | J6: =MIN(10,IF(I6>=0.6,I6*10,0)) -> 0 | K6: 313.49785 | M6: 1328.9875 | N6: =L6/K6-90/365 -> -0.24657534 | O6: 313.49785 | Q6: 17.480036 | R6: 570.33977 | S6: =VLOOKUP(B6,[1]自有品牌手机收入!$F$2:$G$23,2,0)/10000 -> 55.85483 | T6: =S6/(R6*90/365) -> 0.39717091 | U6: =S6/R6-90/365 -> -0.14864279 | V6: 142.58494 | W6: 100.3684 | X6: 9.1509608 | Y6: 1727.427 | Z6: =VLOOKUP(B6,'[1]自有品牌智能硬件收入（已加配额制摊分）'!$H$2:$I$23,2,0)/10000 -> 1147.8148 | AA6: =Z6/(Y6*90/365) -> 2.6947748 | AB6: =Z6/Y6-90/365 -> 0.41788968 | AC6: 31 | AD6: 0.76451327 | AE6: 0 | AF6: 264.81472 | AG6: 19.548958 | AH6: 0.76451327 | AI6: 0 | AJ6: 92.685151 | AK6: 8.0558407 | AL6: 0 | AM6: 待发文后录入 | AN6: 1.5277778 | AO6: 17 | AP6: 17 | AQ6: =VLOOKUP(B6,[1]渠道类指标!$B$2:$F$22,5,0) -> 26 | AR6: 1.6470588 | AS6: 8 | AT6: 19992.119 | AU6: 4998.0296 | AV6: =VLOOKUP(B6,[1]渠道类指标!$B$2:$F$22,4,0) -> 4572 | AW6: 0.83292824 | AX6: 6.6634259 | AY6: 0.18 | AZ6: 0.073529412 | BA6: 0.033 | BB6: 0 | BD6: =MIN(5,BC6*2) -> 0 | BE6: 0.025 | BF6: 0.025 | BG6: 5.1062417 | BH6: 3 | BI6: =H6 -> -0.0096546407 | BL6: 0.83 | BN6: 56.652201 | BO6: 199.61892 | BP6: 0 | BQ6: 0.6 | BR6: 0.024661719 | BS6: 0.024661719 | BT6: 39.866112
A7: 广州运营中心 | B7: 云浮 | C7: 0.048 | D7: =VLOOKUP(B7,'[2]2019年2季度虚拟核算'!C:Q,15,0) -> 0.071235088 | E7: =D7/C7 -> 1.4840643 | F7: =MIN(10,IF(E7>=0.6,E7*10,0)) -> 10 | G7: 0.02 | H7: =VLOOKUP(B7,'[2]2019年2季度虚拟核算'!C:R,16,0) -> 0.026442089 | I7: =H7/G7 -> 1.3221044 | J7: =MIN(10,IF(I7>=0.6,I7*10,0)) -> 10 | K7: 328.40442 | M7: 1174.5078 | N7: =L7/K7-90/365 -> -0.24657534 | O7: 328.40442 | Q7: 20.059506 | R7: 332.76664 | S7: =VLOOKUP(B7,[1]自有品牌手机收入!$F$2:$G$23,2,0)/10000 -> 27.781248 | T7: =S7/(R7*90/365) -> 0.3385808 | U7: =S7/R7-90/365 -> -0.16308967 | V7: 83.191661 | W7: 25.812534 | X7: 0 | Y7: 1262.1638 | Z7: =VLOOKUP(B7,'[1]自有品牌智能硬件收入（已加配额制摊分）'!$H$2:$I$23,2,0)/10000 -> 477.7609 | AA7: =Z7/(Y7*90/365) -> 1.5351303 | AB7: =Z7/Y7-90/365 -> 0.13194993 | AC7: 279.53741 | AD7: 0.087610619 | AE7: 0 | AF7: 202.86168 | AG7: 14.123958 | AH7: 0.087610619 | AI7: 0 | AJ7: 71.001587 | AK7: 0.77265487 | AL7: 0 | AM7: 待发文后录入 | AN7: 3.137012 | AO7: 12 | AP7: 12 | AQ7: =VLOOKUP(B7,[1]渠道类指标!$B$2:$F$22,5,0) -> 8 | AR7: 0.41666667 | AS7: 0 | AT7: 3822.5 | AU7: 955.625 | AV7: =VLOOKUP(B7,[1]渠道类指标!$B$2:$F$22,4,0) -> 2432 | AW7: 0.74506213 | AX7: 0 | AY7: 0.12 | AZ7: 0.049019608 | BA7: 0.1146 | BB7: 5 | BD7: =MIN(5,BC7*2) -> 0 | BE7: 0.025 | BF7: 0.025 | BG7: 1.2686579 | BH7: 3 | BI7: =H7 -> 0.026442089 | BL7: 0 | BN7: 51.196518 | BO7: 116.46833 | BP7: 1.3221044 | BQ7: 0.45 | BR7: 0.0017274947 | BS7: 0.0017274947 | BT7: 46.003901
A8: 广州运营中心 | B8: 合计1 | C8: 0.048 | D8: =VLOOKUP(B8,'[2]2019年2季度虚拟核算'!C:Q,15,0) -> 0.1085066 | E8: =D8/C8 -> 2.2605541 | F8: =MIN(10,IF(E8>=0.6,E8*10,0)) -> 10 | G8: 0.02 | H8: =VLOOKUP(B8,'[2]2019年2季度虚拟核算'!C:R,16,0) -> 0.035016511 | I8: =H8/G8 -> 1.7508255 | J8: =MIN(10,IF(I8>=0.6,I8*10,0)) -> 10 | K8: 32239.155 | M8: 15444.38 | N8: =L8/K8-90/365 -> -0.24657534 | O8: 32239.155 | Q8: 0 | R8: 4079.8078 | S8: =SUM(S3:S7) -> 442.98501 | T8: =S8/(R8*90/365) -> 0.44035171 | U8: =S8/R8-90/365 -> -0.13799547 | V8: 1019.9519 | W8: 488.19782 | X8: 0 | Y8: =SUM(Y3:Y7) -> 15769.071 | Z8: =SUM(Z3:Z7) -> 7305.4518 | AA8: =Z8/(Y8*90/365) -> 1.8788467 | AB8: =Z8/Y8-90/365 -> 0.21670191 | AC8: 2298.2688 | AD8: 1844.1175 | AE8: 8.0239416 | AF8: =SUM(AF3:AF7) -> 2806.4701 | AG8: 212.34792 | AH8: 17.957611 | AI8: 0 | AJ8: =SUM(AJ3:AJ7) -> 982.26453 | AK8: 63.547611 | AL8: 0 | AM8: 待发文后录入 | AN8: 8 | AO8: =SUM(AO3:AO7) -> 120 | AP8: =SUM(AP3:AP7) -> 120 | AQ8: =SUM(AQ3:AQ7) -> 139 | AR8: 1.1 | AS8: 8 | AT8: =SUM(AT3:AT7) -> 174729.46 | AU8: 43682.364 | AV8: =SUM(AV3:AV7) -> 16141 | AW8: 0.3020212 | AX8: 0 | AY8: =SUM(AY3:AY7) -> 3.44 | AZ8: 1.4052288 | BA8: 0.8136 | BB8: 0 | BD8: =MIN(5,BC8*2) -> 0 | BE8: 0.025 | BF8: 0.025 | BG8: 9.5133615 | BH8: 3 | BI8: =H8 -> 0.035016511 | BL8: -2.220446e-17 | BN8: 47.023942 | BO8: 1427.9327 | BP8: 1.5 | BQ8: =SUM(BQ3:BQ7) -> 7.3 | BR8: 0.026946635 | BS8: 0.026946635 | BT8: 43.687217
A9: 深圳运营中心 | B9: 深圳 | C9: 0.048 | D9: =VLOOKUP(B9,'[2]2019年2季度虚拟核算'!C:Q,15,0) -> 0.11891474 | E9: =D9/C9 -> 2.4773904 | F9: =MIN(10,IF(E9>=0.6,E9*10,0)) -> 10 | G9: 0.02 | H9: =VLOOKUP(B9,'[2]2019年2季度虚拟核算'!C:R,16,0) -> 0.063590737 | I9: =H9/G9 -> 3.1795368 | J9: =MIN(10,IF(I9>=0.6,I9*10,0)) -> 10 | K9: 32842.38 | M9: 8947.2119 | N9: =L9/K9-90/365 -> -0.24657534 | O9: 32842.38 | Q9: 0 | R9: 1474.5425 | S9: =VLOOKUP(B9,[1]自有品牌手机收入!$F$2:$G$23,2,0)/10000 -> 24.955766 | T9: =S9/(R9*90/365) -> 0.068637898 | U9: =S9/R9-90/365 -> -0.22965093 | V9: 368.63562 | W9: 18.608477 | X9: 0 | Y9: 7884.8421 | Z9: =VLOOKUP(B9,'[1]自有品牌智能硬件收入（已加配额制摊分）'!$H$2:$I$23,2,0)/10000 -> 3097.7941 | AA9: =Z9/(Y9*90/365) -> 1.5933453 | AB9: =Z9/Y9-90/365 -> 0.14630432 | AC9: 1633.1111 | AD9: 1352.2447 | AE9: 8.2801755 | AF9: 1581.235 | AG9: 120.89583 | AH9: 1.4246903 | AI9: 0 | AJ9: 553.43227 | AK9: 23.132832 | AL9: 0 | AM9: 待发文后录入 | AN9: 0.89577049 | AO9: 62 | AP9: 62 | AQ9: =VLOOKUP(B9,[1]渠道类指标!$B$2:$F$22,5,0) -> 82 | AR9: 1.016129 | AS9: 8 | AT9: 198350.52 | AU9: 49587.631 | AV9: =VLOOKUP(B9,[1]渠道类指标!$B$2:$F$22,4,0) -> 5909 | AW9: 0.21386382 | AX9: 0 | AY9: 1.8 | AZ9: 0.73529412 | BA9: 1.1051 | BB9: 5 | BD9: =MIN(5,BC9*2) -> 0 | BE9: 0.025 | BF9: 0.025 | BG9: -1.7744917 | BH9: 0 | BI9: =H9 -> 0.063590737 | BJ9: 3 | BL9: -1 | BN9: 44.175946 | BO9: 516.08987 | BP9: 1.5 | BQ9: 4.51 | BR9: 0.0036039937 | BS9: 0.0036039937 | BT9: 40.886632
A10: 深圳运营中心 | B10: 汕头 | C10: 0.048 | D10: =VLOOKUP(B10,'[2]2019年2季度虚拟核算'!C:Q,15,0) -> 0.11229545 | E10: =D10/C10 -> 2.3394886 | F10: =MIN(10,IF(E10>=0.6,E10*10,0)) -> 10 | G10: 0.02 | H10: =VLOOKUP(B10,'[2]2019年2季度虚拟核算'!C:R,16,0) -> 0.015233365 | I10: =H10/G10 -> 0.76166824 | J10: =MIN(10,IF(I10>=0.6,I10*10,0)) -> 7.6166824 | K10: 1453.4845 | M10: 2315.6916 | N10: =L10/K10-90/365 -> -0.24657534 | O10: 1453.4845 | Q10: 16.499172 | R10: 714.71893 | S10: =VLOOKUP(B10,[1]自有品牌手机收入!$F$2:$G$23,2,0)/10000 -> 275.20818 | T10: =S10/(R10*90/365) -> 1.5616237 | U10: =S10/R10-90/365 -> 0.13848257 | V10: 178.67973 | W10: 109.57554 | X10: 7.9722643 | Y10: 3350.143 | Z10: =VLOOKUP(B10,'[1]自有品牌智能硬件收入（已加配额制摊分）'!$H$2:$I$23,2,0)/10000 -> 2242.3935 | AA10: =Z10/(Y10*90/365) -> 2.7145561 | AB10: =Z10/Y10-90/365 -> 0.42276726 | AC10: 31 | AD10: 24.684956 | AE10: 7.962889 | AF10: 546.2786 | AG10: 39.630208 | AH10: 24.684956 | AI10: 5.57 | AJ10: 191.19751 | AK10: 25.713274 | AL10: 3.2441508 | AM10: 待发文后录入 | AN10: 1.8350579 | AO10: 33 | AP10: 33 | AQ10: =VLOOKUP(B10,[1]渠道类指标!$B$2:$F$22,5,0) -> 42 | AR10: 1.1212121 | AS10: 8 | AT10: 16741.76 | AU10: 4185.44 | AV10: =VLOOKUP(B10,[1]渠道类指标!$B$2:$F$22,4,0) -> 2222 | AW10: 0.13355824 | AX10: 0 | AY10: 0.58 | AZ10: 0.2369281 | BA10: 0.2643 | BB10: 5 | BD10: =MIN(5,BC10*2) -> 0 | BE10: 0.025 | BF10: 0.025 | BG10: 0.99009468 | BH10: 3 | BI10: =H10 -> 0.015233365 | BL10: 0.17 | BN10: 76.874239 | BO10: 250.15163 | BP10: 0.76166824 | BQ10: 1.31 | BR10: 0.7962889 | BS10: 0.7962889 | BT10: 71.776982
A11: 深圳运营中心 | B11: 揭阳 | C11: 0.048 | D11: =VLOOKUP(B11,'[2]2019年2季度虚拟核算'!C:Q,15,0) -> 0.095114741 | E11: =D11/C11 -> 1.9815571 | F11: =MIN(10,IF(E11>=0.6,E11*10,0)) -> 10 | G11: 0.02 | H11: =VLOOKUP(B11,'[2]2019年2季度虚拟核算'!C:R,16,0) -> -0.04163097 | I11: =H11/G11 -> -2.0815485 | J11: =MIN(10,IF(I11>=0.6,I11*10,0)) -> 0 | K11: 1352.8319 | M11: 1053.8859 | N11: =L11/K11-90/365 -> -0.24657534 | O11: 1352.8319 | Q11: 11.68533 | R11: 307.11015 | S11: =VLOOKUP(B11,[1]自有品牌手机收入!$F$2:$G$23,2,0)/10000 -> 64.99317 | T11: =S11/(R11*90/365) -> 0.85826994 | U11: =S11/R11-90/365 -> -0.034947139 | V11: 76.777538 | W11: 27.315023 | X11: 0 | Y11: 2637.6228 | Z11: =VLOOKUP(B11,'[1]自有品牌智能硬件收入（已加配额制摊分）'!$H$2:$I$23,2,0)/10000 -> 1729.9065 | AA11: =Z11/(Y11*90/365) -> 2.6598693 | AB11: =Z11/Y11-90/365 -> 0.40928284 | AC11: 31 | AD11: 3.500177 | AE11: 0 | AF11: 427.5973 | AG11: 30.639583 | AH11: 3.500177 | AI11: 0 | AJ11: 149.65905 | AK11: 52.508496 | AL11: 5 | AM11: 待发文后录入 | AN11: 3.352981 | AO11: 14 | AP11: 14 | AQ11: =VLOOKUP(B11,[1]渠道类指标!$B$2:$F$22,5,0) -> 13 | AR11: 0.92857143 | AS11: 7.4285714 | AT11: 3317.6 | AU11: 829.4 | AV11: =VLOOKUP(B11,[1]渠道类指标!$B$2:$F$22,4,0) -> 1744 | AW11: 1.3045575 | AX11: 8 | AY11: 0.24 | AZ11: 0.098039216 | BA11: 0.132 | BB11: 5 | BD11: =MIN(5,BC11*2) -> 0 | BE11: 0.025 | BF11: 0.025 | BG11: 0.60879436 | BH11: 3 | BI11: =H11 -> -0.04163097 | BL11: 1.17 | BN11: 54.636883 | BO11: 107.48855 | BP11: 0 | BQ11: 0.99 | BR11: 0.11290894 | BS11: 0.11290894 | BT11: 39.171167
A12: 深圳运营中心 | B12: 梅州 | C12: 0.048 | D12: =VLOOKUP(B12,'[2]2019年2季度虚拟核算'!C:Q,15,0) -> 0.030524666 | E12: =D12/C12 -> 0.63593053 | F12: =MIN(10,IF(E12>=0.6,E12*10,0)) -> 6.3593053 | G12: 0.02 | H12: =VLOOKUP(B12,'[2]2019年2季度虚拟核算'!C:R,16,0) -> -0.0031614799 | I12: =H12/G12 -> -0.15807399 | J12: =MIN(10,IF(I12>=0.6,I12*10,0)) -> 0 | K12: 968.61789 | M12: 1902.1125 | N12: =L12/K12-90/365 -> -0.24657534 | O12: 968.61789 | Q12: 18.292469 | R12: 531.2093 | S12: =VLOOKUP(B12,[1]自有品牌手机收入!$F$2:$G$23,2,0)/10000 -> 123.17975 | T12: =S12/(R12*90/365) -> 0.94042464 | U12: =S12/R12-90/365 -> -0.014689815 | V12: 132.80233 | W12: 1.6840695 | X12: 0 | Y12: 2296.8266 | Z12: =VLOOKUP(B12,'[1]自有品牌智能硬件收入（已加配额制摊分）'!$H$2:$I$23,2,0)/10000 -> 1097.0641 | AA12: =Z12/(Y12*90/365) -> 1.9371095 | AB12: =Z12/Y12-90/365 -> 0.23106809 | AC12: 281.03183 | AD12: 3.2778761 | AE12: 0 | AF12: 350.46311 | AG12: 26.64375 | AH12: 3.2778761 | AI12: 0 | AJ12: 122.66209 | AK12: 22.012035 | AL12: 4.1308065 | AM12: 待发文后录入 | AN12: 3.4896608 | AO12: 31 | AP12: 31 | AQ12: =VLOOKUP(B12,[1]渠道类指标!$B$2:$F$22,5,0) -> 35 | AR12: 1 | AS12: 8 | AT12: 14574.139 | AU12: 3643.5347 | AV12: =VLOOKUP(B12,[1]渠道类指标!$B$2:$F$22,4,0) -> 16686 | AW12: 0.10045191 | AX12: 0 | AY12: 0.3 | AZ12: 0.12254902 | BA12: 0.283 | BB12: 5 | BD12: =MIN(5,BC12*2) -> 0 | BE12: 0.025 | BF12: 0.025 | BG12: 4.1136406 | BH12: 3 | BI12: =H12 -> -0.0031614799 | BJ12: 5 | BL12: 1 | BN12: 54.272242 | BO12: 185.92326 | BP12: -0.15807399 | BQ12: 0.79 | BR12: 0.037411939 | BS12: 0.037411939 | BT12: 37.008279
A13: 深圳运营中心 | B13: 潮州 | C13: 0.048 | D13: =VLOOKUP(B13,'[2]2019年2季度虚拟核算'!C:Q,15,0) -> 0.068668207 | E13: =D13/C13 -> 1.4305877 | F13: =MIN(10,IF(E13>=0.6,E13*10,0)) -> 10 | G13: 0.02 | H13: =VLOOKUP(B13,'[2]2019年2季度虚拟核算'!C:R,16,0) -> 0.0034255038 | I13: =H13/G13 -> 0.17127519 | J13: =MIN(10,IF(I13>=0.6,I13*10,0)) -> 0 | K13: 174.51482 | M13: 592.19642 | N13: =L13/K13-90/365 -> -0.24657534 | O13: 174.51482 | Q13: 16.134734 | R13: 474.89651 | S13: =VLOOKUP(B13,[1]自有品牌手机收入!$F$2:$G$23,2,0)/10000 -> 91.971036 | T13: =S13/(R13*90/365) -> 0.78542091 | U13: =S13/R13-90/365 -> -0.052909913 | V13: 118.72413 | W13: 1.8076126 | X13: 0 | Y13: 1649.0526 | Z13: =VLOOKUP(B13,'[1]自有品牌智能硬件收入（已加配额制摊分）'!$H$2:$I$23,2,0)/10000 -> 850.84736 | AA13: =Z13/(Y13*90/365) -> 2.0925098 | AB13: =Z13/Y13-90/365 -> 0.26938598 | AC13: 138.59147 | AD13: 43.403628 | AE13: 0 | AF13: 258.91242 | AG13: 18.323958 | AH13: 3.6736283 | AI13: 0 | AJ13: 90.619346 | AK13: 54.860265 | AL13: 5 | AM13: 待发文后录入 | AN13: 2.4622916 | AO13: 15 | AP13: 15 | AQ13: =VLOOKUP(B13,[1]渠道类指标!$B$2:$F$22,5,0) -> 17 | AR13: 1.1333333 | AS13: 8 | AT13: 21475.425 | AU13: 5368.8562 | AV13: =VLOOKUP(B13,[1]渠道类指标!$B$2:$F$22,4,0) -> 6756 | AW13: 0.073944986 | AX13: 0 | AY13: 0.14 | AZ13: 0.057189542 | BA13: 0.1384 | BB13: 5 | BD13: =MIN(5,BC13*2) -> 0 | BE13: 0.025 | BF13: 0.025 | BG13: 2.1047924 | BH13: 3 | BI13: =H13 -> 0.0034255038 | BL13: 0 | BN13: 49.597026 | BO13: 166.21378 | BP13: 0 | BQ13: 0.59 | BR13: 0.45920354 | BS13: 0.45920354 | BT13: 38.134188
A14: 深圳运营中心 | B14: 汕尾 | C14: 0.048 | D14: =VLOOKUP(B14,'[2]2019年2季度虚拟核算'!C:Q,15,0) -> 0.091759958 | E14: =D14/C14 -> 1.9116658 | F14: =MIN(10,IF(E14>=0.6,E14*10,0)) -> 10 | G14: 0.02 | H14: =VLOOKUP(B14,'[2]2019年2季度虚拟核算'!C:R,16,0) -> 0.036583086 | I14: =H14/G14 -> 1.8291543 | J14: =MIN(10,IF(I14>=0.6,I14*10,0)) -> 10 | K14: 1264.3394 | M14: 990.19336 | N14: =L14/K14-90/365 -> -0.24657534 | O14: 1264.3394 | Q14: 11.747558 | R14: 133.34812 | S14: =VLOOKUP(B14,[1]自有品牌手机收入!$F$2:$G$23,2,0)/10000 -> 23.976644 | T14: =S14/(R14*90/365) -> 0.72920869 | U14: =S14/R14-90/365 -> -0.066770459 | V14: 33.337031 | W14: 1.8896462 | X14: 0 | Y14: 1224.1447 | Z14: =VLOOKUP(B14,'[1]自有品牌智能硬件收入（已加配额制摊分）'!$H$2:$I$23,2,0)/10000 -> 453.74724 | AA14: =Z14/(Y14*90/365) -> 1.5032514 | AB14: =Z14/Y14-90/365 -> 0.12408938 | AC14: 280.73955 | AD14: 0.012920354 | AE14: 0 | AF14: 186.96581 | AG14: 13.978125 | AH14: 0.012920354 | AI14: 0 | AJ14: 65.438033 | AK14: 0.4 | AL14: 0 | AM14: 待发文后录入 | AN14: 1.2902195 | AO14: 10 | AP14: 10 | AQ14: =VLOOKUP(B14,[1]渠道类指标!$B$2:$F$22,5,0) -> 12 | AR14: 1 | AS14: 8 | AT14: 1690 | AU14: 422.5 | AV14: =VLOOKUP(B14,[1]渠道类指标!$B$2:$F$22,4,0) -> 58 | AW14: 0.24142012 | AX14: 0 | AY14: 0.12 | AZ14: 0.049019608 | BA14: 0.0343 | BB14: 3.4986 | BD14: =MIN(5,BC14*2) -> 0 | BE14: 0.025 | BF14: 0.025 | BG14: -0.89940058 | BH14: 0 | BI14: =H14 -> 0.036583086 | BL14: 0 | BN14: 44.536378 | BO14: 46.671844 | BP14: 1.5 | BQ14: 0.44 | BR14: 0.00027642175 | BS14: 0.00027642175 | BT14: 41.197996
A15: 深圳运营中心 | B15: 合计2 | C15: 0.048 | D15: =VLOOKUP(B15,'[2]2019年2季度虚拟核算'!C:Q,15,0) -> 0.10646079 | E15: =D15/C15 -> 2.2179331 | F15: =MIN(10,IF(E15>=0.6,E15*10,0)) -> 10 | G15: 0.02 | H15: =VLOOKUP(B15,'[2]2019年2季度虚拟核算'!C:R,16,0) -> 0.044547401 | I15: =H15/G15 -> 2.2273701 | J15: =MIN(10,IF(I15>=0.6,I15*10,0)) -> 10 | K15: 38056.168 | M15: 15801.29 | N15: =L15/K15-90/365 -> -0.24657534 | O15: 38056.168 | Q15: 0 | R15: 3635.8255 | S15: =SUM(S9:S14) -> 604.28454 | T15: =S15/(R15*90/365) -> 0.67404487 | U15: =S15/R15-90/365 -> -0.080372497 | V15: 908.95637 | W15: 160.88037 | X15: 0 | Y15: =SUM(Y9:Y14) -> 19042.632 | Z15: =SUM(Z9:Z14) -> 9471.7528 | AA15: =Z15/(Y15*90/365) -> 2.0172222 | AB15: =Z15/Y15-90/365 -> 0.25082191 | AC15: 2395.474 | AD15: 1427.1242 | AE15: 0 | AF15: =SUM(AF9:AF14) -> 3351.4523 | AG15: 250.11146 | AH15: 36.574248 | AI15: 0 | AJ15: =SUM(AJ9:AJ14) -> 1173.0083 | AK15: 178.6269 | AL15: 3.570946 | AM15: 待发文后录入 | AN15: 2.2209969 | AO15: =SUM(AO9:AO14) -> 165 | AP15: =SUM(AP9:AP14) -> 165 | AQ15: =SUM(AQ9:AQ14) -> 201 | AR15: 1.0363636 | AS15: 8 | AT15: =SUM(AT9:AT14) -> 256149.45 | AU15: 64037.362 | AV15: =SUM(AV9:AV14) -> 33375 | AW15: 0.20473985 | AX15: 0 | AY15: =SUM(AY9:AY14) -> 3.18 | AZ15: 1.2990196 | BA15: 1.9571 | BB15: 5 | BD15: =MIN(5,BC15*2) -> 0 | BE15: 0.025 | BF15: 0.025 | BG15: 0.85723829 | BH15: 3 | BI15: =H15 -> 0.044547401 | BJ15: 1.33 | BL15: 0.22333333 | BN15: 43.34861 | BO15: 1272.5389 | BP15: 1.5 | BQ15: =SUM(BQ9:BQ14) -> 8.63 | BR15: 0.060991032 | BS15: 0.060991032 | BT15: 40.494045
A16: 东莞运营中心 | B16: 东莞 | C16: 0.048 | D16: =VLOOKUP(B16,'[2]2019年2季度虚拟核算'!C:Q,15,0) -> 0.061580808 | E16: =D16/C16 -> 1.2829335 | F16: =MIN(10,IF(E16>=0.6,E16*10,0)) -> 10 | G16: 0.02 | H16: =VLOOKUP(B16,'[2]2019年2季度虚拟核算'!C:R,16,0) -> 0.03637868 | I16: =H16/G16 -> 1.818934 | J16: =MIN(10,IF(I16>=0.6,I16*10,0)) -> 10 | K16: 19365.743 | M16: 6910.1898 | N16: =L16/K16-90/365 -> -0.24657534 | O16: 19365.743 | Q16: 0 | R16: 1215.4387 | S16: =VLOOKUP(B16,[1]自有品牌手机收入!$F$2:$G$23,2,0)/10000 -> 22.74087 | T16: =S16/(R16*90/365) -> 0.075879485 | U16: =S16/R16-90/365 -> -0.22786533 | V16: 303.85967 | W16: 63.494793 | X16: 0 | Y16: 5797.1972 | Z16: =VLOOKUP(B16,'[1]自有品牌智能硬件收入（已加配额制摊分）'!$H$2:$I$23,2,0)/10000 -> 2679.7864 | AA16: =Z16/(Y16*90/365) -> 1.8747029 | AB16: =Z16/Y16-90/365 -> 0.21568018 | AC16: 798.53196 | AD16: 2980.5183 | AE16: 15 | AF16: 1112.5606 | AG16: 86.625 | AH16: 0.76831858 | AI16: 0 | AJ16: 389.39619 | AK16: 256.50469 | AL16: 5 | AM16: 待发文后录入 | AN16: 3.2276053 | AO16: 49 | AP16: 49 | AQ16: =VLOOKUP(B16,[1]渠道类指标!$B$2:$F$22,5,0) -> 131 | AR16: 1.0816327 | AS16: 8 | AT16: 162093.72 | AU16: 40523.429 | AV16: =VLOOKUP(B16,[1]渠道类指标!$B$2:$F$22,4,0) -> 8192 | AW16: 0.11430425 | AX16: 0 | AY16: 0.86 | AZ16: 0.35130719 | BA16: 0.954 | BB16: 5 | BD16: =MIN(5,BC16*2) -> 0 | BE16: 0.025 | BF16: 0.025 | BG16: 1.8732347 | BH16: 3 | BI16: =H16 -> 0.03637868 | BL16: 0.33 | BN16: 59.557605 | BO16: 425.40354 | BP16: 1.5 | BQ16: 3.05 | BR16: 0.0027623434 | BS16: 0.0027623434 | BT16: 55.115463
A17: 东莞运营中心 | B17: 中山 | C17: 0.048 | D17: =VLOOKUP(B17,'[2]2019年2季度虚拟核算'!C:Q,15,0) -> 0.095489951 | E17: =D17/C17 -> 1.989374 | F17: =MIN(10,IF(E17>=0.6,E17*10,0)) -> 10 | G17: 0.02 | H17: =VLOOKUP(B17,'[2]2019年2季度虚拟核算'!C:R,16,0) -> 0.055365241 | I17: =H17/G17 -> 2.768262 | J17: =MIN(10,IF(I17>=0.6,I17*10,0)) -> 10 | K17: 343.81073 | M17: 3043.717 | N17: =L17/K17-90/365 -> -0.24657534 | O17: 343.81073 | Q17: 20.294914 | R17: 843.28211 | S17: =VLOOKUP(B17,[1]自有品牌手机收入!$F$2:$G$23,2,0)/10000 -> 26.376398 | T17: =S17/(R17*90/365) -> 0.12685073 | U17: =S17/R17-90/365 -> -0.21529708 | V17: 210.82053 | W17: 14.826193 | X17: 0 | Y17: 3459.4354 | Z17: =VLOOKUP(B17,'[1]自有品牌智能硬件收入（已加配额制摊分）'!$H$2:$I$23,2,0)/10000 -> 364.67077 | AA17: =Z17/(Y17*90/365) -> 0.42750981 | AB17: =Z17/Y17-90/365 -> -0.14116196 | AC17: 117.6208 | AD17: 458.68774 | AE17: 12.569199 | AF17: 605.29232 | AG17: 41.788542 | AH17: 1.7927434 | AI17: 0 | AJ17: 211.85231 | AK17: 8.6499115 | AL17: 0 | AM17: 待发文后录入 | AN17: 1.8030071 | AO17: 23 | AP17: 23 | AQ17: =VLOOKUP(B17,[1]渠道类指标!$B$2:$F$22,5,0) -> 39 | AR17: 1.6086957 | AS17: 8 | AT17: 38377 | AU17: 9594.25 | AV17: =VLOOKUP(B17,[1]渠道类指标!$B$2:$F$22,4,0) -> 9234 | AW17: 0.70021106 | AX17: 0 | AY17: 0.54 | AZ17: 0.22058824 | BA17: 0.0182 | BB17: 0 | BD17: =MIN(5,BC17*2) -> 0 | BE17: 0.025 | BF17: 0.025 | BG17: 1.0074006 | BH17: 3 | BI17: =H17 -> 0.055365241 | BL17: 0.17 | BN17: 65.837121 | BO17: 295.14874 | BP17: 1.5 | BQ17: 1.53 | BR17: 0.087111209 | BS17: 0.087111209 | BT17: 61.759609
A18: 东莞运营中心 | B18: 惠州 | C18: 0.048 | D18: =VLOOKUP(B18,'[2]2019年2季度虚拟核算'!C:Q,15,0) -> 0.085461008 | E18: =D18/C18 -> 1.7804377 | F18: =MIN(10,IF(E18>=0.6,E18*10,0)) -> 10 | G18: 0.02 | H18: =VLOOKUP(B18,'[2]2019年2季度虚拟核算'!C:R,16,0) -> 0.056715486 | I18: =H18/G18 -> 2.8357743 | J18: =MIN(10,IF(I18>=0.6,I18*10,0)) -> 10 | K18: 1882.9413 | M18: 5388.8579 | N18: =L18/K18-90/365 -> -0.24657534 | O18: 1882.9413 | Q18: 22.5 | R18: 911.56853 | S18: =VLOOKUP(B18,[1]自有品牌手机收入!$F$2:$G$23,2,0)/10000 -> 106.89024 | T18: =S18/(R18*90/365) -> 0.47555318 | U18: =S18/R18-90/365 -> -0.12931565 | V18: 227.89213 | W18: 62.526782 | X18: 0 | Y18: 3570.5519 | Z18: =VLOOKUP(B18,'[1]自有品牌智能硬件收入（已加配额制摊分）'!$H$2:$I$23,2,0)/10000 -> 1869.8369 | AA18: =Z18/(Y18*90/365) -> 2.123825 | AB18: =Z18/Y18-90/365 -> 0.27710753 | AC18: 272.49427 | AD18: 1191.9643 | AE18: 14.514959 | AF18: 625.74505 | AG18: 44.821875 | AH18: 0.064336283 | AI18: 0 | AJ18: 219.01077 | AK18: 27.993628 | AL18: 3.1227641 | AM18: 待发文后录入 | AN18: 2.1839642 | AO18: 57 | AP18: 57 | AQ18: =VLOOKUP(B18,[1]渠道类指标!$B$2:$F$22,5,0) -> 113 | AR18: 1.3684211 | AS18: 8 | AT18: 19186.2 | AU18: 4796.55 | AV18: =VLOOKUP(B18,[1]渠道类指标!$B$2:$F$22,4,0) -> 7441 | AW18: 0.9965496 | AX18: 7.9723968 | AY18: 0.52 | AZ18: 0.2124183 | BA18: 0.3721 | BB18: 5 | BD18: =MIN(5,BC18*2) -> 0 | BE18: 0.025 | BF18: 0.025 | BG18: -0.22643156 | BH18: 0 | BI18: =H18 -> 0.056715486 | BJ18: 1 | BL18: -1.5 | BN18: 82.794084 | BO18: 319.04899 | BP18: 1.5 | BQ18: 1.59 | BR18: 0.00041126195 | BS18: 0.00041126195 | BT18: 76.589635
A19: 东莞运营中心 | B19: 珠海 | C19: 0.048 | D19: =VLOOKUP(B19,'[2]2019年2季度虚拟核算'!C:Q,15,0) -> 0.092829455 | E19: =D19/C19 -> 1.933947 | F19: =MIN(10,IF(E19>=0.6,E19*10,0)) -> 10 | G19: 0.02 | H19: =VLOOKUP(B19,'[2]2019年2季度虚拟核算'!C:R,16,0) -> 0.051169291 | I19: =H19/G19 -> 2.5584645 | J19: =MIN(10,IF(I19>=0.6,I19*10,0)) -> 10 | K19: 2273.6935 | M19: 3433.6068 | N19: =L19/K19-90/365 -> -0.24657534 | O19: 2273.6935 | Q19: 22.5 | R19: 391.49987 | S19: =VLOOKUP(B19,[1]自有品牌手机收入!$F$2:$G$23,2,0)/10000 -> 3.937701 | T19: =S19/(R19*90/365) -> 0.040790729 | U19: =S19/R19-90/365 -> -0.23651735 | V19: 97.874968 | W19: 1.3639824 | X19: 0 | Y19: 1974.6823 | Z19: =VLOOKUP(B19,'[1]自有品牌智能硬件收入（已加配额制摊分）'!$H$2:$I$23,2,0)/10000 -> 807.91733 | AA19: =Z19/(Y19*90/365) -> 1.6592814 | AB19: =Z19/Y19-90/365 -> 0.16256253 | AC19: 376.86656 | AD19: 496.31801 | AE19: 12.04022 | AF19: 332.89759 | AG19: 23.048958 | AH19: -0.30699115 | AI19: 0 | AJ19: 116.51416 | AK19: -5.549292 | AL19: 0 | AM19: 待发文后录入 | AN19: 3.9913573 | AO19: 24 | AP19: 24 | AQ19: =VLOOKUP(B19,[1]渠道类指标!$B$2:$F$22,5,0) -> 28 | AR19: 1.125 | AS19: 8 | AT19: 22816.8 | AU19: 5704.2 | AV19: =VLOOKUP(B19,[1]渠道类指标!$B$2:$F$22,4,0) -> 8383 | AW19: 0.74822061 | AX19: 0 | AY19: 0.3 | AZ19: 0.12254902 | BA19: 0.2495 | BB19: 5 | BD19: =MIN(5,BC19*2) -> 0 | BE19: 0.025 | BF19: 0.025 | BG19: -0.51259319 | BH19: 0 | BI19: =H19 -> 0.051169291 | BL19: 1.83 | BN19: 73.361578 | BO19: 137.02495 | BP19: 1.5 | BQ19: 0.84 | BR19: -0.0036887158 | BS19: -0.0036887158 | BT19: 67.818868
A20: 东莞运营中心 | B20: 河源 | C20: 0.048 | D20: =VLOOKUP(B20,'[2]2019年2季度虚拟核算'!C:Q,15,0) -> 0.077010384 | E20: =D20/C20 -> 1.604383 | F20: =MIN(10,IF(E20>=0.6,E20*10,0)) -> 10 | G20: 0.02 | H20: =VLOOKUP(B20,'[2]2019年2季度虚拟核算'!C:R,16,0) -> 0.028222907 | I20: =H20/G20 -> 1.4111453 | J20: =MIN(10,IF(I20>=0.6,I20*10,0)) -> 10 | K20: 1120.6037 | M20: 858.62095 | N20: =L20/K20-90/365 -> -0.24657534 | O20: 1120.6037 | Q20: 11.493193 | R20: 375.47377 | S20: =VLOOKUP(B20,[1]自有品牌手机收入!$F$2:$G$23,2,0)/10000 -> 9.006724 | T20: =S20/(R20*90/365) -> 0.097283145 | U20: =S20/R20-90/365 -> -0.22258772 | V20: 93.868443 | W20: 12.570441 | X20: 0 | Y20: 1451.7612 | Z20: =VLOOKUP(B20,'[1]自有品牌智能硬件收入（已加配额制摊分）'!$H$2:$I$23,2,0)/10000 -> 197.64622 | AA20: =Z20/(Y20*90/365) -> 0.55213295 | AB20: =Z20/Y20-90/365 -> -0.11043297 | AC20: 362.94031 | AD20: 0.3680531 | AE20: 0 | AF20: 230.90488 | AG20: 16.661458 | AH20: 0.3680531 | AI20: 0 | AJ20: 80.816707 | AK20: 1.1047788 | AL20: 0 | AM20: 待发文后录入 | AN20: 2.2232545 | AO20: 20 | AP20: 20 | AQ20: =VLOOKUP(B20,[1]渠道类指标!$B$2:$F$22,5,0) -> 46 | AR20: 1.95 | AS20: 8 | AT20: 12481.65 | AU20: 3120.4126 | AV20: =VLOOKUP(B20,[1]渠道类指标!$B$2:$F$22,4,0) -> 1779 | AW20: 0.87007725 | AX20: 6.960618 | AY20: 0.2 | AZ20: 0.081699346 | BA20: 0.0664 | BB20: 4.06368 | BD20: =MIN(5,BC20*2) -> 0 | BE20: 0.025 | BF20: 0.025 | BG20: 1.4831288 | BH20: 3 | BI20: =H20 -> 0.028222907 | BL20: 1.17 | BN20: 56.910746 | BO20: 131.41582 | BP20: 1.4111453 | BQ20: 0.55 | BR20: 0.0063758393 | BS20: 0.0063758393 | BT20: 51.93835
A21: 东莞运营中心 | B21: 合计3 | C21: 0.048 | D21: =VLOOKUP(B21,'[2]2019年2季度虚拟核算'!C:Q,15,0) -> 0.07846888 | E21: =D21/C21 -> 1.6347683 | F21: =MIN(10,IF(E21>=0.6,E21*10,0)) -> 10 | G21: 0.02 | H21: =VLOOKUP(B21,'[2]2019年2季度虚拟核算'!C:R,16,0) -> 0.046755917 | I21: =H21/G21 -> 2.3377959 | J21: =MIN(10,IF(I21>=0.6,I21*10,0)) -> 10 | K21: 24986.793 | M21: 19634.99 | N21: =L21/K21-90/365 -> -0.24657534 | O21: 24986.793 | Q21: 11.787223 | R21: 3737.263 | S21: =SUM(S16:S20) -> 168.95194 | T21: =S21/(R21*90/365) -> 0.18334112 | U21: =S21/R21-90/365 -> -0.20136794 | V21: 934.31574 | W21: 154.78219 | X21: 0 | Y21: =SUM(Y16:Y20) -> 16253.628 | Z21: =SUM(Z16:Z20) -> 5919.8576 | AA21: =Z21/(Y21*90/365) -> 1.4771048 | AB21: =Z21/Y21-90/365 -> 0.11764227 | AC21: 1928.4539 | AD21: 5127.8565 | AE21: 13.665981 | AF21: =SUM(AF16:AF20) -> 2907.4004 | AG21: 212.94583 | AH21: 2.6864602 | AI21: 0 | AJ21: =SUM(AJ16:AJ20) -> 1017.5901 | AK21: 288.70372 | AL21: 5 | AM21: 待发文后录入 | AN21: 2.6858377 | AO21: =SUM(AO16:AO20) -> 173 | AP21: =SUM(AP16:AP20) -> 173 | AQ21: =SUM(AQ16:AQ20) -> 357 | AR21: 1.3526012 | AS21: 8 | AT21: =SUM(AT16:AT20) -> 254955.37 | AU21: 63738.842 | AV21: =SUM(AV16:AV20) -> 35029 | AW21: 0.36262033 | AX21: 0 | AY21: =SUM(AY16:AY20) -> 2.42 | AZ21: 0.98856209 | BA21: 1.6602 | BB21: 5 | BD21: =MIN(5,BC21*2) -> 0 | BE21: 0.025 | BF21: 0.025 | BG21: 0.72494786 | BH21: 3 | BI21: =H21 -> 0.046755917 | BJ21: 0.2 | BL21: 0.4 | BN21: 69.739041 | BO21: 1308.042 | BP21: 1.5 | BQ21: =SUM(BQ16:BQ20) -> 7.56 | BR21: 0.0045066748 | BS21: 0.0045066748 | BT21: 64.555757
A22: 佛山运营中心 | B22: 佛山 | C22: 0.048 | D22: =VLOOKUP(B22,'[2]2019年2季度虚拟核算'!C:Q,15,0) -> 0.15591121 | E22: =D22/C22 -> 3.2481501 | F22: =MIN(10,IF(E22>=0.6,E22*10,0)) -> 10 | G22: 0.02 | H22: =VLOOKUP(B22,'[2]2019年2季度虚拟核算'!C:R,16,0) -> 0.019563072 | I22: =H22/G22 -> 0.9781536 | J22: =MIN(10,IF(I22>=0.6,I22*10,0)) -> 9.781536 | K22: 8404.5965 | M22: 3851.6059 | N22: =L22/K22-90/365 -> -0.24657534 | O22: 8404.5965 | Q22: 0 | R22: 902.06423 | S22: =VLOOKUP(B22,[1]自有品牌手机收入!$F$2:$G$23,2,0)/10000 -> 35.694675 | T22: =S22/(R22*90/365) -> 0.1604783 | U22: =S22/R22-90/365 -> -0.20700535 | V22: 225.51606 | W22: 13.603275 | X22: 0 | Y22: 5228.8938 | Z22: =VLOOKUP(B22,'[1]自有品牌智能硬件收入（已加配额制摊分）'!$H$2:$I$23,2,0)/10000 -> 1845.1953 | AA22: =Z22/(Y22*90/365) -> 1.4311425 | AB22: =Z22/Y22-90/365 -> 0.10630911 | AC22: 1292.1409 | AD22: 400.44912 | AE22: 0 | AF22: 914.58992 | AG22: 70.576042 | AH22: 3.149115 | AI22: 0 | AJ22: 320.10647 | AK22: 5.5916814 | AL22: 0 | AM22: 待发文后录入 | AN22: 0.36104757 | AO22: 23 | AP22: 23 | AQ22: =VLOOKUP(B22,[1]渠道类指标!$B$2:$F$22,5,0) -> 38 | AR22: 1.0434783 | AS22: 8 | AT22: 40333.7 | AU22: 10083.425 | AV22: =VLOOKUP(B22,[1]渠道类指标!$B$2:$F$22,4,0) -> 24049 | AW22: 0.17494056 | AX22: 0 | AY22: 0.76 | AZ22: 0.31045752 | BA22: 0.3319 | BB22: 5 | BD22: =MIN(5,BC22*2) -> 0 | BE22: 0.025 | BF22: 0.025 | BG22: 1.131575 | BH22: 3 | BI22: =H22 -> 0.019563072 | BL22: -1.33 | BN22: 34.812584 | BO22: 315.72248 | BP22: 0.9781536 | BQ22: 2.32 | BR22: 0.013772796 | BS22: 0.013772796 | BT22: 29.548537
A23: 佛山运营中心 | B23: 江门 | C23: 0.048 | D23: =VLOOKUP(B23,'[2]2019年2季度虚拟核算'!C:Q,15,0) -> 0.072006354 | E23: =D23/C23 -> 1.5001324 | F23: =MIN(10,IF(E23>=0.6,E23*10,0)) -> 10 | G23: 0.02 | H23: =VLOOKUP(B23,'[2]2019年2季度虚拟核算'!C:R,16,0) -> -0.01573246 | I23: =H23/G23 -> -0.786623 | J23: =MIN(10,IF(I23>=0.6,I23*10,0)) -> 0 | K23: 421.17765 | M23: 769.20583 | N23: =L23/K23-90/365 -> -0.24657534 | O23: 421.17765 | Q23: 15.532841 | R23: 453.74866 | S23: =VLOOKUP(B23,[1]自有品牌手机收入!$F$2:$G$23,2,0)/10000 -> 47.967176 | T23: =S23/(R23*90/365) -> 0.42872534 | U23: =S23/R23-90/365 -> -0.14086225 | V23: 113.43716 | W23: 1.4605303 | X23: 0 | Y23: 3540.346 | Z23: =VLOOKUP(B23,'[1]自有品牌智能硬件收入（已加配额制摊分）'!$H$2:$I$23,2,0)/10000 -> 1736.5674 | AA23: =Z23/(Y23*90/365) -> 1.9892817 | AB23: =Z23/Y23-90/365 -> 0.24393248 | AC23: 387.6402 | AD23: 2.8610619 | AE23: 0 | AF23: 577.51985 | AG23: 40.213542 | AH23: 2.8610619 | AI23: 0 | AJ23: 202.13195 | AK23: 22.950619 | AL23: 0 | AM23: 待发文后录入 | AN23: 3.4725998 | AO23: 24 | AP23: 24 | AQ23: =VLOOKUP(B23,[1]渠道类指标!$B$2:$F$22,5,0) -> 30 | AR23: 1 | AS23: 8 | AT23: 14681.457 | AU23: 3670.3643 | AV23: =VLOOKUP(B23,[1]渠道类指标!$B$2:$F$22,4,0) -> 5178 | AW23: 0.29969778 | AX23: 0 | AY23: 1.6 | AZ23: 0.65359477 | BA23: 0.9469 | BB23: 5 | BD23: =MIN(5,BC23*2) -> 0 | BE23: 0.025 | BF23: 0.025 | BG23: -3.2114746 | BH23: 0 | BI23: =H23 -> -0.01573246 | BL23: -1.5 | BN23: 40.505441 | BO23: 158.81203 | BP23: 0 | BQ23: 1.35 | BR23: 0.019816198 | BS23: 0.019816198 | BT23: 28.474208
A24: 佛山运营中心 | B24: 湛江 | C24: 0.048 | D24: =VLOOKUP(B24,'[2]2019年2季度虚拟核算'!C:Q,15,0) -> 0.096458147 | E24: =D24/C24 -> 2.0095447 | F24: =MIN(10,IF(E24>=0.6,E24*10,0)) -> 10 | G24: 0.02 | H24: =VLOOKUP(B24,'[2]2019年2季度虚拟核算'!C:R,16,0) -> 0.025186624 | I24: =H24/G24 -> 1.2593312 | J24: =MIN(10,IF(I24>=0.6,I24*10,0)) -> 10 | K24: 2304.0853 | M24: 397.96413 | N24: =L24/K24-90/365 -> -0.24657534 | O24: 2304.0853 | Q24: 0 | R24: 1184.4022 | S24: =VLOOKUP(B24,[1]自有品牌手机收入!$F$2:$G$23,2,0)/10000 -> 10.582606 | T24: =S24/(R24*90/365) -> 0.036236293 | U24: =S24/R24-90/365 -> -0.23764037 | V24: 296.10056 | W24: 2.6330943 | X24: 0 | Y24: 3604.7726 | Z24: =VLOOKUP(B24,'[1]自有品牌智能硬件收入（已加配额制摊分）'!$H$2:$I$23,2,0)/10000 -> 2323.1478 | AA24: =Z24/(Y24*90/365) -> 2.6136614 | AB24: =Z24/Y24-90/365 -> 0.3978891 | AC24: 31 | AD24: 30.915841 | AE24: 9.9728518 | AF24: 593.22231 | AG24: 42.466667 | AH24: 30.915841 | AI24: 6.98 | AJ24: 207.62781 | AK24: 50.661947 | AL24: 5 | AM24: 待发文后录入 | AN24: 0.88888889 | AO24: 20 | AP24: 20 | AQ24: =VLOOKUP(B24,[1]渠道类指标!$B$2:$F$22,5,0) -> 33 | AR24: 1.35 | AS24: 8 | AT24: 22812.679 | AU24: 5703.1697 | AV24: =VLOOKUP(B24,[1]渠道类指标!$B$2:$F$22,4,0) -> 3066 | AW24: 0.12308945 | AX24: 0 | AY24: 0.26 | AZ24: 0.10620915 | BA24: 0.1507 | BB24: 5 | BD24: =MIN(5,BC24*2) -> 0 | BE24: 0.025 | BF24: 0.025 | BG24: 1.6219123 | BH24: 3 | BI24: =H24 -> 0.025186624 | BL24: 0 | BN24: 58.842737 | BO24: 414.54078 | BP24: 1.2593312 | BQ24: 1.43 | BR24: 0.99728518 | BS24: 0.99728518 | BT24: 61.107739
A25: 佛山运营中心 | B25: 茂名 | C25: 0.048 | D25: =VLOOKUP(B25,'[2]2019年2季度虚拟核算'!C:Q,15,0) -> 0.097471966 | E25: =D25/C25 -> 2.0306659 | F25: =MIN(10,IF(E25>=0.6,E25*10,0)) -> 10 | G25: 0.02 | H25: =VLOOKUP(B25,'[2]2019年2季度虚拟核算'!C:R,16,0) -> 0.048696374 | I25: =H25/G25 -> 2.4348187 | J25: =MIN(10,IF(I25>=0.6,I25*10,0)) -> 10 | K25: 795.49148 | M25: 2783.7137 | N25: =L25/K25-90/365 -> -0.24657534 | O25: 795.49148 | Q25: 20.961925 | R25: 497.97423 | S25: =VLOOKUP(B25,[1]自有品牌手机收入!$F$2:$G$23,2,0)/10000 -> 132.76502 | T25: =S25/(R25*90/365) -> 1.0812525 | U25: =S25/R25-90/365 -> 0.020034875 | V25: 124.49356 | W25: 32.969047 | X25: 0 | Y25: 2423.9824 | Z25: =VLOOKUP(B25,'[1]自有品牌智能硬件收入（已加配额制摊分）'!$H$2:$I$23,2,0)/10000 -> 1673.691 | AA25: =Z25/(Y25*90/365) -> 2.8002459 | AB25: =Z25/Y25-90/365 -> 0.44389625 | AC25: 31 | AD25: 7.2471681 | AE25: 0 | AF25: 383.65154 | AG25: 29.18125 | AH25: 7.2471681 | AI25: 0 | AJ25: 134.27804 | AK25: 31.197788 | AL25: 5 | AM25: 待发文后录入 | AN25: 2.2222222 | AO25: 10 | AP25: 10 | AQ25: =VLOOKUP(B25,[1]渠道类指标!$B$2:$F$22,5,0) -> 12 | AR25: 1.6 | AS25: 8 | AT25: 8374.6 | AU25: 2093.65 | AV25: =VLOOKUP(B25,[1]渠道类指标!$B$2:$F$22,4,0) -> 5151 | AW25: 1.8302964 | AX25: 8 | AY25: 0.32 | AZ25: 0.13071895 | BA25: 0.1847 | BB25: 5 | BD25: =MIN(5,BC25*2) -> 0 | BE25: 0.025 | BF25: 0.025 | BG25: -0.052286765 | BH25: 0 | BI25: =H25 -> 0.048696374 | BL25: -1.5 | BN25: 67.684147 | BO25: 174.29098 | BP25: 1.5 | BQ25: 0.89 | BR25: 0.23377962 | BS25: 0.23377962 | BT25: 64.981312
A26: 佛山运营中心 | B26: 阳江 | C26: 0.048 | D26: =VLOOKUP(B26,'[2]2019年2季度虚拟核算'!C:Q,15,0) -> 0.14330852 | E26: =D26/C26 -> 2.9855941 | F26: =MIN(10,IF(E26>=0.6,E26*10,0)) -> 10 | G26: 0.02 | H26: =VLOOKUP(B26,'[2]2019年2季度虚拟核算'!C:R,16,0) -> -0.023051175 | I26: =H26/G26 -> -1.1525588 | J26: =MIN(10,IF(I26>=0.6,I26*10,0)) -> 0 | K26: 163.63456 | M26: 812.32233 | N26: =L26/K26-90/365 -> -0.24657534 | O26: 163.63456 | Q26: 16.872005 | R26: 508.91439 | S26: =VLOOKUP(B26,[1]自有品牌手机收入!$F$2:$G$23,2,0)/10000 -> 127.63379 | T26: =S26/(R26*90/365) -> 1.0171179 | U26: =S26/R26-90/365 -> 0.0042208483 | V26: 127.2286 | W26: 37.933389 | X26: 0 | Y26: 1488.5746 | Z26: =VLOOKUP(B26,'[1]自有品牌智能硬件收入（已加配额制摊分）'!$H$2:$I$23,2,0)/10000 -> 599.13646 | AA26: =Z26/(Y26*90/365) -> 1.6323208 | AB26: =Z26/Y26-90/365 -> 0.15591471 | AC26: 50.611536 | AD26: 11.71823 | AE26: 0 | AF26: 233.79363 | AG26: 17.157292 | AH26: 11.71823 | AI26: 8.43 | AJ26: 81.827769 | AK26: 21.98 | AL26: 5 | AM26: 待发文后录入 | AN26: 3.7625971 | AO26: 16 | AP26: 16 | AQ26: =VLOOKUP(B26,[1]渠道类指标!$B$2:$F$22,5,0) -> 19 | AR26: 1.0625 | AS26: 8 | AT26: 8260.824 | AU26: 2065.206 | AV26: =VLOOKUP(B26,[1]渠道类指标!$B$2:$F$22,4,0) -> 1886 | AW26: 0.42949711 | AX26: 0 | AY26: 0.26 | AZ26: 0.10620915 | BA26: 0.0806 | BB26: 3.7944 | BD26: =MIN(5,BC26*2) -> 0 | BE26: 0.025 | BF26: 0.025 | BG26: 1.8008578 | BH26: 3 | BI26: =H26 -> -0.023051175 | BL26: -0.5 | BN26: 58.363017 | BO26: 178.12004 | BP26: 0 | BQ26: 0.51 | BR26: 1.4741797 | BS26: 1.4741797 | BT26: 53.759749
A27: 佛山运营中心 | B27: 合计4 | C27: 0.048 | D27: =VLOOKUP(B27,'[2]2019年2季度虚拟核算'!C:Q,15,0) -> 0.12551763 | E27: =D27/C27 -> 2.6149506 | F27: =MIN(10,IF(E27>=0.6,E27*10,0)) -> 10 | G27: 0.02 | H27: =VLOOKUP(B27,'[2]2019年2季度虚拟核算'!C:R,16,0) -> 0.018784103 | I27: =H27/G27 -> 0.93920513 | J27: =MIN(10,IF(I27>=0.6,I27*10,0)) -> 9.3920513 | K27: 12088.985 | M27: 8614.8119 | N27: =L27/K27-90/365 -> -0.24657534 | O27: 12088.985 | Q27: 10.689249 | R27: 3547.1037 | S27: =SUM(S22:S26) -> 354.64326 | T27: =S27/(R27*90/365) -> 0.40547883 | U27: =S27/R27-90/365 -> -0.14659426 | V27: 886.77594 | W27: 88.599335 | X27: 0 | Y27: =SUM(Y22:Y26) -> 16286.569 | Z27: =SUM(Z22:Z26) -> 8177.7379 | AA27: =Z27/(Y27*90/365) -> 2.0363571 | AB27: =Z27/Y27-90/365 -> 0.2555401 | AC27: 1792.3926 | AD27: 453.19142 | AE27: 0 | AF27: =SUM(AF22:AF26) -> 2702.7772 | AG27: 199.59479 | AH27: 55.891416 | AI27: 0 | AJ27: =SUM(AJ22:AJ26) -> 945.97203 | AK27: 132.38204 | AL27: 3.3162698 | AM27: 待发文后录入 | AN27: 2.1414711 | AO27: =SUM(AO22:AO26) -> 93 | AP27: =SUM(AP22:AP26) -> 93 | AQ27: =SUM(AQ22:AQ26) -> 132 | AR27: 1.1612903 | AS27: 8 | AT27: =SUM(AT22:AT26) -> 94463.26 | AU27: 23615.815 | AV27: =SUM(AV22:AV26) -> 39330 | AW27: 0.35082423 | AX27: 0 | AY27: =SUM(AY22:AY26) -> 3.2 | AZ27: 1.3071895 | BA27: 1.6948 | BB27: 5 | BD27: =MIN(5,BC27*2) -> 0 | BE27: 0.025 | BF27: 0.025 | BG27: 0.25811673 | BH27: 3 | BI27: =H27 -> 0.018784103 | BL27: -0.966 | BN27: 50.573041 | BO27: 1241.4863 | BP27: 0.93920513 | BQ27: =SUM(BQ22:BQ26) -> 6.5 | BR27: 0.12617244 | BS27: 0.12617244 | BT27: 43.483037
A28: 全省 | B28: 全省合计 | C28: 0.04 | D28: =VLOOKUP(B28,'[2]2019年2季度虚拟核算'!C:Q,15,0) -> 0.099492612 | E28: =D28/C28 -> 2.4873153 | F28: =MIN(10,IF(E28>=0.6,E28*10,0)) -> 10 | G28: 0.02 | H28: =VLOOKUP(B28,'[2]2019年2季度虚拟核算'!C:R,16,0) -> 0.03943987 | I28: =H28/G28 -> 1.9719935 | J28: =MIN(10,IF(I28>=0.6,I28*10,0)) -> 10 | K28: 107371.1 | M28: 59495.47 | N28: =L28/K28-90/365 -> -0.24657534 | O28: 107371.1 | Q28: 0 | R28: =R27+R21+R15+R8 -> 15000 | S28: =S8+S15+S21+S27 -> 1570.8648 | T28: =S28/(R28*90/365) -> 0.42471529 | U28: =S28/R28-90/365 -> -0.14185103 | V28: 3750 | W28: 892.45972 | X28: 0 | Y28: =Y27+Y21+Y15+Y8 -> 67351.9 | Z28: =Z8+Z15+Z21+Z27 -> 30874.8 | AA28: =Z28/(Y28*90/365) -> 1.8591082 | AB28: =Z28/Y28-90/365 -> 0.21183489 | AC28: 8414.5893 | AD28: 8852.2896 | AE28: 10.112631 | AF28: =AF27+AF21+AF15+AF8 -> 11768.1 | AG28: 875 | AH28: 113.10973 | AI28: 0 | AJ28: =AJ27+AJ21+AJ15+AJ8 -> 4118.835 | AK28: 663.26027 | AL28: 3.7900587 | AN28: 3.7620764 | AO28: =AO27+AO21+AO15+AO8 -> 551 | AP28: =AP27+AP21+AP15+AP8 -> 551 | AQ28: =AQ27+AQ21+AQ15+AQ8 -> 829 | AR28: 1.1705989 | AS28: 8 | AT28: =AT27+AT21+AT15+AT8 -> 780297.53 | AU28: 195074.38 | AV28: =AV27+AV21+AV15+AV8 -> 123875 | AW28: 0.29579486 | AX28: 0 | AY28: =AY27+AY21+AY15+AY8 -> 12.24 | AZ28: 5 | BA28: 6.1257 | BB28: 5 | BD28: =MIN(5,BC28*2) -> 0 | BE28: 0.025 | BF28: 0.025 | BG28: 2.8384161 | BH28: 3 | BI28: =H28 -> 0.03943987 | BJ28: 0.77 | BL28: -0.085666667 | BN28: 54.345766 | BO28: 5250 | BP28: 1.5 | BQ28: =BQ27+BQ21+BQ15+BQ8 -> 29.99 | BR28: 0.049067994 | BS28: 0.049067994 | BT28: 50.66983
A29: 分值 | B29: 分值 | F29: 10 | J29: 10 | Q29: 13 | X29: 15 | AE29: 10 | AI29: 7 | AL29: 10 | AN29: 9 | AS29: 8 | AX29: 8 | BB29: 5 | BD29: 5 | BH29: 3 | BJ29: 5 | BL29: 2 | BM29: -10
